{"id":"ekstep.learning.item.read","ver":"1.0","ts":"2018-10-26T07:45:35ZZ","params":{"resmsgid":"8deaa62f-6d20-447b-878d-3cfdbca1d1d9","msgid":null,"err":null,"status":"successful","errmsg":null},"responseCode":"OK","result":{"assessment_item":{"template":"NA","templateType":"Horizontal","isPartialScore":true,"itemType":"UNIT","code":"NA","subject":"English","qlevel":"EASY","channel":"01246375399411712074","language":["English"],"medium":"English","title":"Q 1. CHARBHUJANATH TEMPLE C-3 ENG.","type":"mcq","body":"{\"data\":{\"plugin\":{\"id\":\"org.ekstep.questionunit.mcq\",\"version\":\"1.1\",\"templateId\":\"horizontalMCQ\"},\"data\":{\"question\":{\"text\":\"<p>WHERE IS THE CHARBHUJANATH TEMPLE</p>\\n\\n<p>(चारभुजा नाथ मंदिर कहां&nbsp;&nbsp;स्थित&nbsp;है )</p>\\n\",\"image\":\"\",\"audio\":\"\",\"audioName\":\"\",\"hint\":\"\"},\"options\":[{\"text\":\"<p>JODHPUR</p>\\n\",\"image\":\"\",\"audio\":\"\",\"audioName\":\"\",\"hint\":\"\",\"isCorrect\":false,\"$$hashKey\":\"object:1416\"},{\"text\":\"<p>KOTA</p>\\n\",\"image\":\"\",\"audio\":\"\",\"audioName\":\"\",\"hint\":\"\",\"isCorrect\":false,\"$$hashKey\":\"object:1417\"},{\"text\":\"<p>JAIPUR</p>\\n\",\"image\":\"\",\"audio\":\"\",\"audioName\":\"\",\"isCorrect\":false,\"$$hashKey\":\"object:1427\"},{\"text\":\"<p>NAGOUR</p>\\n\",\"image\":\"\",\"audio\":\"\",\"audioName\":\"\",\"isCorrect\":true,\"$$hashKey\":\"object:1432\"}],\"questionCount\":0,\"media\":[]},\"config\":{\"metadata\":{\"max_score\":1,\"isShuffleOption\":false,\"isPartialScore\":true,\"templateType\":\"Horizontal\",\"name\":\"Q 1. CHARBHUJANATH TEMPLE C-3 ENG.\",\"title\":\"Q 1. CHARBHUJANATH TEMPLE C-3 ENG.\",\"board\":\"State (Rajasthan)\",\"medium\":\"English\",\"gradeLevel\":[\"Class 3\"],\"subject\":\"English\",\"qlevel\":\"EASY\",\"category\":\"MCQ\"},\"max_time\":0,\"max_score\":1,\"partial_scoring\":true,\"layout\":\"Horizontal\",\"isShuffleOption\":false,\"questionCount\":1},\"media\":[]}}","createdOn":"2018-10-24T07:25:52.006+0000","gradeLevel":["Class 3"],"isShuffleOption":false,"appId":"prod.diksha.portal","options":[{"answer":true,"value":{"type":"text","asset":"1","resvalue":0,"resindex":0}}],"lastUpdatedOn":"2018-10-24T07:25:52.006+0000","identifier":"do_31261867787883315221651","consumerId":"150610ca-4ffb-4e0a-b4ef-c1305e9100d5","version":2,"versionKey":"1540365952006","framework":"rj_k-12","createdBy":"4c52d606-596e-4a91-b555-9484cc44a3b5","max_score":1,"name":"Q 1. CHARBHUJANATH TEMPLE C-3 ENG.","template_id":"NA","category":"MCQ","board":"State (Rajasthan)","status":"Live"}}}