{"id":"ekstep.learning.item.read","ver":"1.0","ts":"2018-10-26T07:59:18ZZ","params":{"resmsgid":"5ce0a0ef-9e04-4cd1-aedc-90c218599a7d","msgid":null,"err":null,"status":"successful","errmsg":null},"responseCode":"OK","result":{"assessment_item":{"templateType":"Vertical2","template":"NA","isPartialScore":true,"itemType":"UNIT","code":"NA","data":"{\"plugin\":{\"id\":\"org.ekstep.questionunit.mcq\",\"version\":\"1.1\",\"templateId\":\"horizontalMCQ\"},\"data\":{\"question\":{\"text\":\"<p>&nbsp;অসমৰ&nbsp;&nbsp;&nbsp;প্রথম মুখ্যমন্ত্রীৰ নাম&nbsp;কি ?</p>\\n\",\"image\":\"\",\"audio\":\"\",\"audioName\":\"\",\"hint\":\"\"},\"options\":[{\"text\":\"<p><font style=\\\"color: rgb(0, 0, 0); font-family: asfont; font-style: normal; font-variant-ligatures: normal; font-variant-caps: normal; font-weight: 400; letter-spacing: normal; orphans: 2; text-align: start; text-indent: 0px; text-transform: none; white-space: normal; widows: 2; word-spacing: 0px; -webkit-text-stroke-width: 0px; text-decoration-style: initial; text-decoration-color: initial;\\\"><font size=\\\"4\\\">&nbsp;</font><span style=\\\"font-size: 25px;\\\">&nbsp;</span></font>&nbsp;ক.&nbsp;&nbsp;বিষ্ণুৰ৷ম&nbsp;মেধি</p>\\n\",\"image\":\"\",\"audio\":\"\",\"audioName\":\"\",\"hint\":\"\",\"isCorrect\":false,\"$$hashKey\":\"object:11491\"},{\"text\":\"<p>খ .&nbsp;বিমল৷&nbsp;প্রসাধ</p>\\n\",\"image\":\"\",\"audio\":\"\",\"audioName\":\"\",\"hint\":\"\",\"isCorrect\":false,\"$$hashKey\":\"object:11492\"},{\"text\":\"<p style=\\\"text-align: start;\\\"><font color=\\\"#000000\\\" face=\\\"asfont\\\" size=\\\"4\\\">&nbsp; &nbsp; &nbsp; &nbsp; &nbsp; &nbsp; &nbsp; &nbsp; &nbsp; &nbsp; &nbsp; &nbsp; &nbsp; &nbsp; &nbsp; &nbsp; &nbsp; &nbsp; &nbsp; &nbsp; &nbsp; &nbsp; &nbsp; &nbsp; &nbsp; &nbsp; &nbsp; &nbsp; &nbsp; &nbsp; &nbsp; &nbsp; &nbsp;</font><font color=\\\"#000000\\\"><font face=\\\"asfont\\\"><font style=\\\"color: rgb(0, 0, 0); font-family: asfont; font-size: 25px; font-style: normal; font-variant-ligatures: normal; font-variant-caps: normal; font-weight: 400; letter-spacing: normal; orphans: 2; text-align: start; text-indent: 0px; text-transform: none; white-space: normal; widows: 2; word-spacing: 0px; -webkit-text-stroke-width: 0px; text-decoration-style: initial; text-decoration-color: initial;\\\"><font size=\\\"4\\\">&nbsp;</font><font size=\\\"2\\\">&nbsp;&nbsp;</font></font></font></font><font size=\\\"2\\\"><font style=\\\"color: rgb(0, 0, 0); font-family: asfont; font-style: normal; font-variant-ligatures: normal; font-variant-caps: normal; font-weight: 400; letter-spacing: normal; orphans: 2; text-align: start; text-indent: 0px; text-transform: none; white-space: normal; widows: 2; word-spacing: 0px; -webkit-text-stroke-width: 0px; text-decoration-style: initial; text-decoration-color: initial;\\\">গ.&nbsp;লোকপ্রিয়<font color=\\\"#212121\\\"><font><font face=\\\"inherit\\\">&nbsp;</font></font></font><font color=\\\"#212121\\\"><font><span style=\\\"white-space:pre-wrap\\\">গোপীনাথ </span></font></font>বৰদলৈ</font></font></p>\\n\",\"image\":\"\",\"audio\":\"\",\"audioName\":\"\",\"isCorrect\":true,\"$$hashKey\":\"object:11502\"},{\"text\":\"<p>&nbsp;ঘ .&nbsp;ওপৰত&nbsp;উল্লেখ&nbsp;কৰ৷&nbsp;এটাও নহয়</p>\\n\",\"image\":\"\",\"audio\":\"\",\"audioName\":\"\",\"isCorrect\":false,\"$$hashKey\":\"object:11507\"}],\"questionCount\":0,\"media\":[]},\"config\":{\"metadata\":{\"max_score\":1,\"isShuffleOption\":false,\"isPartialScore\":true,\"templateType\":\"Horizontal\",\"name\":\" অসমৰ   প্রথম মুখ্যমন্ত্রী নাম হল\\n\",\"title\":\" অসমৰ   প্রথম মুখ্যমন্ত্রী নাম হল\\n\",\"description\":\"অসমৰ   প্রথম মুখ্যমন্ত্রী\",\"board\":\"State (Assam)\",\"gradeLevel\":[\"Class 7\"],\"medium\":\"Assamese\",\"subject\":\"Social Science\",\"qlevel\":\"MEDIUM\",\"category\":\"MCQ\"},\"max_time\":0,\"max_score\":1,\"partial_scoring\":true,\"layout\":\"Horizontal\",\"isShuffleOption\":false,\"questionCount\":1},\"media\":[]}","subject":"Social Science","qlevel":"MEDIUM","channel":"01254290140407398431","description":"অসমৰ   প্রথম মুখ্যমন্ত্রী","language":["English"],"medium":"Assamese","type":"mcq","title":" অসমৰ   প্রথম মুখ্যমন্ত্রী নাম হল\n","body":"{\"data\":{\"plugin\":{\"id\":\"org.ekstep.questionunit.mcq\",\"version\":\"1.1\",\"templateId\":\"horizontalMCQ\"},\"data\":{\"question\":{\"text\":\"<p>&nbsp;অসমৰ&nbsp;&nbsp;&nbsp;প্রথম মুখ্যমন্ত্রীৰ নাম&nbsp;কি ?</p>\\n\",\"image\":\"\",\"audio\":\"\",\"audioName\":\"\",\"hint\":\"\"},\"options\":[{\"text\":\"<p><font style=\\\"color: rgb(0, 0, 0); font-family: asfont; font-style: normal; font-variant-ligatures: normal; font-variant-caps: normal; font-weight: 400; letter-spacing: normal; orphans: 2; text-align: start; text-indent: 0px; text-transform: none; white-space: normal; widows: 2; word-spacing: 0px; -webkit-text-stroke-width: 0px; text-decoration-style: initial; text-decoration-color: initial;\\\"><font size=\\\"4\\\">&nbsp;</font><span style=\\\"font-size: 25px;\\\">&nbsp;</span></font>&nbsp;ক.&nbsp;&nbsp;বিষ্ণুৰ৷ম&nbsp;মেধি</p>\\n\",\"image\":\"\",\"audio\":\"\",\"audioName\":\"\",\"hint\":\"\",\"isCorrect\":false,\"$$hashKey\":\"object:11491\"},{\"text\":\"<p>খ .&nbsp;বিমল৷&nbsp;প্রসাধ</p>\\n\",\"image\":\"\",\"audio\":\"\",\"audioName\":\"\",\"hint\":\"\",\"isCorrect\":false,\"$$hashKey\":\"object:11492\"},{\"text\":\"<p style=\\\"text-align: start;\\\"><font color=\\\"#000000\\\" face=\\\"asfont\\\" size=\\\"4\\\">&nbsp; &nbsp; &nbsp; &nbsp; &nbsp; &nbsp; &nbsp; &nbsp; &nbsp; &nbsp; &nbsp; &nbsp; &nbsp; &nbsp; &nbsp; &nbsp; &nbsp; &nbsp; &nbsp; &nbsp; &nbsp; &nbsp; &nbsp; &nbsp; &nbsp; &nbsp; &nbsp; &nbsp; &nbsp; &nbsp; &nbsp; &nbsp; &nbsp;</font><font color=\\\"#000000\\\"><font face=\\\"asfont\\\"><font style=\\\"color: rgb(0, 0, 0); font-family: asfont; font-size: 25px; font-style: normal; font-variant-ligatures: normal; font-variant-caps: normal; font-weight: 400; letter-spacing: normal; orphans: 2; text-align: start; text-indent: 0px; text-transform: none; white-space: normal; widows: 2; word-spacing: 0px; -webkit-text-stroke-width: 0px; text-decoration-style: initial; text-decoration-color: initial;\\\"><font size=\\\"4\\\">&nbsp;</font><font size=\\\"2\\\">&nbsp;&nbsp;</font></font></font></font><font size=\\\"2\\\"><font style=\\\"color: rgb(0, 0, 0); font-family: asfont; font-style: normal; font-variant-ligatures: normal; font-variant-caps: normal; font-weight: 400; letter-spacing: normal; orphans: 2; text-align: start; text-indent: 0px; text-transform: none; white-space: normal; widows: 2; word-spacing: 0px; -webkit-text-stroke-width: 0px; text-decoration-style: initial; text-decoration-color: initial;\\\">গ.&nbsp;লোকপ্রিয়<font color=\\\"#212121\\\"><font><font face=\\\"inherit\\\">&nbsp;</font></font></font><font color=\\\"#212121\\\"><font><span style=\\\"white-space:pre-wrap\\\">গোপীনাথ </span></font></font>বৰদলৈ</font></font></p>\\n\",\"image\":\"\",\"audio\":\"\",\"audioName\":\"\",\"isCorrect\":true,\"$$hashKey\":\"object:11502\"},{\"text\":\"<p>&nbsp;ঘ .&nbsp;ওপৰত&nbsp;উল্লেখ&nbsp;কৰ৷&nbsp;এটাও নহয়</p>\\n\",\"image\":\"\",\"audio\":\"\",\"audioName\":\"\",\"isCorrect\":false,\"$$hashKey\":\"object:11507\"}],\"questionCount\":0,\"media\":[]},\"config\":{\"metadata\":{\"data\":{\"plugin\":{\"id\":\"org.ekstep.questionunit.mcq\",\"version\":\"1.1\",\"templateId\":\"horizontalMCQ\"},\"data\":{\"question\":{\"text\":\"<p>&nbsp;অসমৰ&nbsp;&nbsp;&nbsp;প্রথম মুখ্যমন্ত্রীৰ নাম&nbsp;কি ?</p>\\n\",\"image\":\"\",\"audio\":\"\",\"audioName\":\"\",\"hint\":\"\"},\"options\":[{\"text\":\"<p><font style=\\\"color: rgb(0, 0, 0); font-family: asfont; font-style: normal; font-variant-ligatures: normal; font-variant-caps: normal; font-weight: 400; letter-spacing: normal; orphans: 2; text-align: start; text-indent: 0px; text-transform: none; white-space: normal; widows: 2; word-spacing: 0px; -webkit-text-stroke-width: 0px; text-decoration-style: initial; text-decoration-color: initial;\\\"><font size=\\\"4\\\">&nbsp;</font><span style=\\\"font-size: 25px;\\\">&nbsp;</span></font>&nbsp;ক.&nbsp;&nbsp;বিষ্ণুৰ৷ম&nbsp;মেধি</p>\\n\",\"image\":\"\",\"audio\":\"\",\"audioName\":\"\",\"hint\":\"\",\"isCorrect\":false,\"$$hashKey\":\"object:11491\"},{\"text\":\"<p>খ .&nbsp;বিমল৷&nbsp;প্রসাধ</p>\\n\",\"image\":\"\",\"audio\":\"\",\"audioName\":\"\",\"hint\":\"\",\"isCorrect\":false,\"$$hashKey\":\"object:11492\"},{\"text\":\"<p style=\\\"text-align: start;\\\"><font color=\\\"#000000\\\" face=\\\"asfont\\\" size=\\\"4\\\">&nbsp; &nbsp; &nbsp; &nbsp; &nbsp; &nbsp; &nbsp; &nbsp; &nbsp; &nbsp; &nbsp; &nbsp; &nbsp; &nbsp; &nbsp; &nbsp; &nbsp; &nbsp; &nbsp; &nbsp; &nbsp; &nbsp; &nbsp; &nbsp; &nbsp; &nbsp; &nbsp; &nbsp; &nbsp; &nbsp; &nbsp; &nbsp; &nbsp;</font><font color=\\\"#000000\\\"><font face=\\\"asfont\\\"><font style=\\\"color: rgb(0, 0, 0); font-family: asfont; font-size: 25px; font-style: normal; font-variant-ligatures: normal; font-variant-caps: normal; font-weight: 400; letter-spacing: normal; orphans: 2; text-align: start; text-indent: 0px; text-transform: none; white-space: normal; widows: 2; word-spacing: 0px; -webkit-text-stroke-width: 0px; text-decoration-style: initial; text-decoration-color: initial;\\\"><font size=\\\"4\\\">&nbsp;</font><font size=\\\"2\\\">&nbsp;&nbsp;</font></font></font></font><font size=\\\"2\\\"><font style=\\\"color: rgb(0, 0, 0); font-family: asfont; font-style: normal; font-variant-ligatures: normal; font-variant-caps: normal; font-weight: 400; letter-spacing: normal; orphans: 2; text-align: start; text-indent: 0px; text-transform: none; white-space: normal; widows: 2; word-spacing: 0px; -webkit-text-stroke-width: 0px; text-decoration-style: initial; text-decoration-color: initial;\\\">গ.&nbsp;লোকপ্রিয়<font color=\\\"#212121\\\"><font><font face=\\\"inherit\\\">&nbsp;</font></font></font><font color=\\\"#212121\\\"><font><span style=\\\"white-space:pre-wrap\\\">গোপীনাথ </span></font></font>বৰদলৈ</font></font></p>\\n\",\"image\":\"\",\"audio\":\"\",\"audioName\":\"\",\"isCorrect\":true,\"$$hashKey\":\"object:11502\"},{\"text\":\"<p>&nbsp;ঘ .&nbsp;ওপৰত&nbsp;উল্লেখ&nbsp;কৰ৷&nbsp;এটাও নহয়</p>\\n\",\"image\":\"\",\"audio\":\"\",\"audioName\":\"\",\"isCorrect\":false,\"$$hashKey\":\"object:11507\"}],\"questionCount\":0,\"media\":[]},\"config\":{\"metadata\":{\"max_score\":1,\"isShuffleOption\":false,\"isPartialScore\":true,\"templateType\":\"Horizontal\",\"name\":\" অসমৰ   প্রথম মুখ্যমন্ত্রী নাম হল\\n\",\"title\":\" অসমৰ   প্রথম মুখ্যমন্ত্রী নাম হল\\n\",\"description\":\"অসমৰ   প্রথম মুখ্যমন্ত্রী\",\"board\":\"State (Assam)\",\"gradeLevel\":[\"Class 7\"],\"medium\":\"Assamese\",\"subject\":\"Social Science\",\"qlevel\":\"MEDIUM\",\"category\":\"MCQ\"},\"max_time\":0,\"max_score\":1,\"partial_scoring\":true,\"layout\":\"Horizontal\",\"isShuffleOption\":false,\"questionCount\":1},\"media\":[]},\"medium\":\"Assamese\",\"questionTitle\":\" অসমৰ   প্রথম মুখ্যমন্ত্রী নাম হল\\n\",\"qlevel\":\"MEDIUM\",\"subject\":\"Social Science\",\"board\":\"State (Assam)\",\"templateType\":\"Vertical2\",\"isPartialScore\":true,\"gradeLevel\":[\"Class 7\"],\"isShuffleOption\":false,\"questionDesc\":\"অসমৰ   প্রথম মুখ্যমন্ত্রী\",\"max_score\":1,\"name\":\" অসমৰ   প্রথম মুখ্যমন্ত্রী নাম হল\\n\",\"title\":\" অসমৰ   প্রথম মুখ্যমন্ত্রী নাম হল\\n\",\"category\":\"MCQ\"},\"max_time\":0,\"max_score\":1,\"partial_scoring\":true,\"layout\":\"Vertical2\",\"isShuffleOption\":false,\"questionCount\":1},\"media\":[]}}","createdOn":"2018-10-21T10:45:57.866+0000","gradeLevel":["Class 7"],"isShuffleOption":false,"appId":"prod.diksha.portal","options":[{"answer":true,"value":{"type":"text","asset":"1","resvalue":0,"resindex":0}}],"lastUpdatedOn":"2018-10-21T13:46:05.749+0000","questionDesc":"অসমৰ   প্রথম মুখ্যমন্ত্রী","identifier":"do_31261665286444646421045","questionTitle":" অসমৰ   প্রথম মুখ্যমন্ত্রী নাম হল\n","consumerId":"150610ca-4ffb-4e0a-b4ef-c1305e9100d5","version":2,"versionKey":"1540129565749","framework":"as_k-12","createdBy":"62d25659-b2d5-49da-8591-58f3f895a8ae","max_score":1,"name":" অসমৰ   প্রথম মুখ্যমন্ত্রী নাম হল\n","template_id":"NA","category":"MCQ","board":"State (Assam)","status":"Live"}}}