{"id":"ekstep.learning.item.read","ver":"1.0","ts":"2018-10-26T07:59:12ZZ","params":{"resmsgid":"8c72321f-48f0-4c14-805b-9154359a0f6d","msgid":null,"err":null,"status":"successful","errmsg":null},"responseCode":"OK","result":{"assessment_item":{"template":"NA","templateType":"Horizontal","isPartialScore":true,"itemType":"UNIT","code":"NA","data":"{\"plugin\":{\"id\":\"org.ekstep.questionunit.mcq\",\"version\":\"1.1\",\"templateId\":\"horizontalMCQ\"},\"data\":{\"question\":{\"text\":\"<p>&nbsp;৬| &quot;যি&nbsp;চৰকাৰে&nbsp;সকলো&nbsp;শ্ৰেনীৰ&nbsp;মানুহৰ&nbsp;মাজত&nbsp;অর্থনৈতিক সমতাৰ&nbsp;যোগেদি&nbsp;সমাজত&nbsp;ন্য়ায়&nbsp;স্থাপনকৰিব&nbsp;বিচাৰে;তেনে&nbsp;চৰকাৰী&nbsp;ব্য়ৱস্থাকে&nbsp;সমাজতান্ত্ৰিক&nbsp;চৰকাৰ&nbsp;বোলে,&nbsp;যেনে-&nbsp;চীন&nbsp;দেশ&nbsp;|&nbsp;ওপৰোক্ত বাক্য়শাৰী&nbsp;সত্য&nbsp;নে&nbsp;?&nbsp;</p>\\n\",\"image\":\"\",\"audio\":\"\",\"audioName\":\"\",\"hint\":\"\"},\"options\":[{\"text\":\"<p>ক&nbsp;&nbsp;অসত্য</p>\\n\",\"image\":\"\",\"audio\":\"\",\"audioName\":\"\",\"hint\":\"\",\"isCorrect\":false,\"$$hashKey\":\"object:1107\"},{\"text\":\"<p>খ&nbsp;সত্য়</p>\\n\",\"image\":\"\",\"audio\":\"\",\"audioName\":\"\",\"hint\":\"\",\"isCorrect\":true,\"$$hashKey\":\"object:1108\"},{\"text\":\"<p>গ&nbsp;দুয়োটা&nbsp;অসত্য়</p>\\n\",\"image\":\"\",\"audio\":\"\",\"audioName\":\"\",\"isCorrect\":false,\"$$hashKey\":\"object:1118\"}],\"questionCount\":0,\"media\":[]},\"config\":{\"metadata\":{\"max_score\":1,\"isShuffleOption\":false,\"isPartialScore\":true,\"templateType\":\"Grid\",\"name\":\" ৬| \\\"যি চৰকাৰে সকলো শ্ৰেনীৰ মানুহৰ মাজত অর্থনৈতিক সমতাৰ যোগেদি সমাজত ন্য়ায় স্থাপনকৰিব বিচাৰে;তেনে চৰকাৰী ব্য়ৱস্থাকে সমাজতান্ত্ৰিক চৰকাৰ বোলে, যেনে- চীন দেশ | ওপৰোক্ত বাক্য়শাৰী সত্য নে ? \\n\",\"title\":\" ৬| \\\"যি চৰকাৰে সকলো শ্ৰেনীৰ মানুহৰ মাজত অর্থনৈতিক সমতাৰ যোগেদি সমাজত ন্য়ায় স্থাপনকৰিব বিচাৰে;তেনে চৰকাৰী ব্য়ৱস্থাকে সমাজতান্ত্ৰিক চৰকাৰ বোলে, যেনে- চীন দেশ | ওপৰোক্ত বাক্য়শাৰী সত্য নে ? \\n\",\"description\":\"সমাজতান্ত্ৰিক চৰকাৰ\",\"board\":\"State (Assam)\",\"gradeLevel\":[\"Class 6\"],\"qlevel\":\"EASY\",\"medium\":\"Assamese\",\"subject\":\"Social Science\",\"category\":\"MCQ\"},\"max_time\":0,\"max_score\":1,\"partial_scoring\":true,\"layout\":\"Grid\",\"isShuffleOption\":false,\"questionCount\":1},\"media\":[]}","subject":"Social Science","qlevel":"EASY","channel":"01254290140407398431","description":"সমাজতান্ত্ৰিক চৰকাৰ","language":["English"],"medium":"Assamese","title":"৬| \"যি চৰকাৰে সকলো শ্ৰেনীৰ মানুহৰ মাজত অর্থনৈতিক ৰী ব্য়ৱস্থাকে সমতাৰ যোগেদি সমাজত ন্য়ায় স্থাপনকৰিব বিচাৰে;তেনে চৰকাসমাজতান্ত্ৰিক চৰকাৰ বোলে, যেনে- চীন দেশ | ওপৰোক্ত বাক্য়শাৰী সত্য নে ?","type":"mcq","body":"{\"data\":{\"plugin\":{\"id\":\"org.ekstep.questionunit.mcq\",\"version\":\"1.1\",\"templateId\":\"horizontalMCQ\"},\"data\":{\"question\":{\"text\":\"<p>&nbsp;৬| &quot;যি&nbsp;চৰকাৰে&nbsp;সকলো&nbsp;শ্ৰেনীৰ&nbsp;মানুহৰ&nbsp;মাজত&nbsp;অর্থনৈতিক সমতাৰ&nbsp;যোগেদি&nbsp;সমাজত&nbsp;ন্য়ায়&nbsp;স্থাপনকৰিব&nbsp;বিচাৰে;তেনে&nbsp;চৰকাৰী&nbsp;ব্য়ৱস্থাকে&nbsp;সমাজতান্ত্ৰিক&nbsp;চৰকাৰ&nbsp;বোলে,&nbsp;যেনে-&nbsp;চীন&nbsp;দেশ&nbsp;|&nbsp;ওপৰোক্ত বাক্য়শাৰী&nbsp;সত্য&nbsp;নে&nbsp;?&nbsp;</p>\\n\",\"image\":\"\",\"audio\":\"\",\"audioName\":\"\",\"hint\":\"\"},\"options\":[{\"text\":\"<p>ক&nbsp;&nbsp;অসত্য</p>\\n\",\"image\":\"\",\"audio\":\"\",\"audioName\":\"\",\"hint\":\"\",\"isCorrect\":false,\"$$hashKey\":\"object:1107\"},{\"text\":\"<p>খ&nbsp;সত্য়</p>\\n\",\"image\":\"\",\"audio\":\"\",\"audioName\":\"\",\"hint\":\"\",\"isCorrect\":true,\"$$hashKey\":\"object:1108\"},{\"text\":\"<p>গ&nbsp;দুয়োটা&nbsp;অসত্য়</p>\\n\",\"image\":\"\",\"audio\":\"\",\"audioName\":\"\",\"isCorrect\":false,\"$$hashKey\":\"object:1118\"}],\"questionCount\":0,\"media\":[]},\"config\":{\"metadata\":{\"data\":{\"plugin\":{\"id\":\"org.ekstep.questionunit.mcq\",\"version\":\"1.1\",\"templateId\":\"horizontalMCQ\"},\"data\":{\"question\":{\"text\":\"<p>&nbsp;৬| &quot;যি&nbsp;চৰকাৰে&nbsp;সকলো&nbsp;শ্ৰেনীৰ&nbsp;মানুহৰ&nbsp;মাজত&nbsp;অর্থনৈতিক সমতাৰ&nbsp;যোগেদি&nbsp;সমাজত&nbsp;ন্য়ায়&nbsp;স্থাপনকৰিব&nbsp;বিচাৰে;তেনে&nbsp;চৰকাৰী&nbsp;ব্য়ৱস্থাকে&nbsp;সমাজতান্ত্ৰিক&nbsp;চৰকাৰ&nbsp;বোলে,&nbsp;যেনে-&nbsp;চীন&nbsp;দেশ&nbsp;|&nbsp;ওপৰোক্ত বাক্য়শাৰী&nbsp;সত্য&nbsp;নে&nbsp;?&nbsp;</p>\\n\",\"image\":\"\",\"audio\":\"\",\"audioName\":\"\",\"hint\":\"\"},\"options\":[{\"text\":\"<p>ক&nbsp;&nbsp;অসত্য</p>\\n\",\"image\":\"\",\"audio\":\"\",\"audioName\":\"\",\"hint\":\"\",\"isCorrect\":false,\"$$hashKey\":\"object:1107\"},{\"text\":\"<p>খ&nbsp;সত্য়</p>\\n\",\"image\":\"\",\"audio\":\"\",\"audioName\":\"\",\"hint\":\"\",\"isCorrect\":true,\"$$hashKey\":\"object:1108\"},{\"text\":\"<p>গ&nbsp;দুয়োটা&nbsp;অসত্য়</p>\\n\",\"image\":\"\",\"audio\":\"\",\"audioName\":\"\",\"isCorrect\":false,\"$$hashKey\":\"object:1118\"}],\"questionCount\":0,\"media\":[]},\"config\":{\"metadata\":{\"max_score\":1,\"isShuffleOption\":false,\"isPartialScore\":true,\"templateType\":\"Grid\",\"name\":\" ৬| \\\"যি চৰকাৰে সকলো শ্ৰেনীৰ মানুহৰ মাজত অর্থনৈতিক সমতাৰ যোগেদি সমাজত ন্য়ায় স্থাপনকৰিব বিচাৰে;তেনে চৰকাৰী ব্য়ৱস্থাকে সমাজতান্ত্ৰিক চৰকাৰ বোলে, যেনে- চীন দেশ | ওপৰোক্ত বাক্য়শাৰী সত্য নে ? \\n\",\"title\":\" ৬| \\\"যি চৰকাৰে সকলো শ্ৰেনীৰ মানুহৰ মাজত অর্থনৈতিক সমতাৰ যোগেদি সমাজত ন্য়ায় স্থাপনকৰিব বিচাৰে;তেনে চৰকাৰী ব্য়ৱস্থাকে সমাজতান্ত্ৰিক চৰকাৰ বোলে, যেনে- চীন দেশ | ওপৰোক্ত বাক্য়শাৰী সত্য নে ? \\n\",\"description\":\"সমাজতান্ত্ৰিক চৰকাৰ\",\"board\":\"State (Assam)\",\"gradeLevel\":[\"Class 6\"],\"qlevel\":\"EASY\",\"medium\":\"Assamese\",\"subject\":\"Social Science\",\"category\":\"MCQ\"},\"max_time\":0,\"max_score\":1,\"partial_scoring\":true,\"layout\":\"Grid\",\"isShuffleOption\":false,\"questionCount\":1},\"media\":[]},\"medium\":\"Assamese\",\"questionTitle\":\" ৬| \\\"যি চৰকাৰে সকলো শ্ৰেনীৰ মানুহৰ মাজত অর্থনৈতিক সমতাৰ যোগেদি সমাজত ন্য়ায় স্থাপনকৰিব বিচাৰে;তেনে চৰকাৰী ব্য়ৱস্থাকে সমাজতান্ত্ৰিক চৰকাৰ বোলে, যেনে- চীন দেশ | ওপৰোক্ত বাক্য়শাৰী সত্য নে ? \\n\",\"qlevel\":\"EASY\",\"subject\":\"Social Science\",\"board\":\"State (Assam)\",\"templateType\":\"Horizontal\",\"isPartialScore\":true,\"gradeLevel\":[\"Class 6\"],\"isShuffleOption\":false,\"questionDesc\":\"সমাজতান্ত্ৰিক চৰকাৰ\",\"max_score\":1,\"name\":\"৬| \\\"যি চৰকাৰে সকলো শ্ৰেনীৰ মানুহৰ মাজত অর্থনৈতিক ৰী ব্য়ৱস্থাকে সমতাৰ যোগেদি সমাজত ন্য়ায় স্থাপনকৰিব বিচাৰে;তেনে চৰকাসমাজতান্ত্ৰিক চৰকাৰ বোলে, যেনে- চীন দেশ | ওপৰোক্ত বাক্য়শাৰী সত্য নে ?\",\"title\":\"৬| \\\"যি চৰকাৰে সকলো শ্ৰেনীৰ মানুহৰ মাজত অর্থনৈতিক ৰী ব্য়ৱস্থাকে সমতাৰ যোগেদি সমাজত ন্য়ায় স্থাপনকৰিব বিচাৰে;তেনে চৰকাসমাজতান্ত্ৰিক চৰকাৰ বোলে, যেনে- চীন দেশ | ওপৰোক্ত বাক্য়শাৰী সত্য নে ?\",\"description\":\"সমাজতান্ত্ৰিক চৰকাৰ\",\"category\":\"MCQ\"},\"max_time\":0,\"max_score\":1,\"partial_scoring\":true,\"layout\":\"Horizontal\",\"isShuffleOption\":false,\"questionCount\":1},\"media\":[]}}","createdOn":"2018-10-22T07:20:51.870+0000","gradeLevel":["Class 6"],"isShuffleOption":false,"appId":"prod.diksha.portal","options":[{"answer":true,"value":{"type":"text","asset":"1","resvalue":0,"resindex":0}}],"lastUpdatedOn":"2018-10-22T09:23:32.964+0000","questionDesc":"সমাজতান্ত্ৰিক চৰকাৰ","identifier":"do_3126172598425272321889","questionTitle":" ৬| \"যি চৰকাৰে সকলো শ্ৰেনীৰ মানুহৰ মাজত অর্থনৈতিক সমতাৰ যোগেদি সমাজত ন্য়ায় স্থাপনকৰিব বিচাৰে;তেনে চৰকাৰী ব্য়ৱস্থাকে সমাজতান্ত্ৰিক চৰকাৰ বোলে, যেনে- চীন দেশ | ওপৰোক্ত বাক্য়শাৰী সত্য নে ? \n","consumerId":"150610ca-4ffb-4e0a-b4ef-c1305e9100d5","version":2,"versionKey":"1540200212964","framework":"as_k-12","createdBy":"62d25659-b2d5-49da-8591-58f3f895a8ae","max_score":1,"name":"৬| \"যি চৰকাৰে সকলো শ্ৰেনীৰ মানুহৰ মাজত অর্থনৈতিক ৰী ব্য়ৱস্থাকে সমতাৰ যোগেদি সমাজত ন্য়ায় স্থাপনকৰিব বিচাৰে;তেনে চৰকাসমাজতান্ত্ৰিক চৰকাৰ বোলে, যেনে- চীন দেশ | ওপৰোক্ত বাক্য়শাৰী সত্য নে ?","template_id":"NA","category":"MCQ","board":"State (Assam)","status":"Live"}}}