{"id":"ekstep.learning.item.read","ver":"1.0","ts":"2018-10-26T07:59:14ZZ","params":{"resmsgid":"5c2c551a-7592-43d2-9152-ddfc64a4bcf7","msgid":null,"err":null,"status":"successful","errmsg":null},"responseCode":"OK","result":{"assessment_item":{"template":"NA","templateType":"Horizontal","isPartialScore":true,"itemType":"UNIT","code":"NA","subject":"Botany","qlevel":"MEDIUM","channel":"in.ekstep","language":["English"],"medium":"Tamil","title":"LCMMQK-Q28-படிம வளர்ச்சி (development) படிநிலையை சரியாக வரிசைப்படுத்து.","type":"mcq","body":"{\"data\":{\"plugin\":{\"id\":\"org.ekstep.questionunit.mcq\",\"version\":\"1.1\",\"templateId\":\"horizontalMCQ\"},\"data\":{\"question\":{\"text\":\"<p>படிம வளர்ச்சி (development) படிநிலையை சரியாக வரிசைப்படுத்து.&nbsp;&nbsp;&nbsp;&nbsp;&nbsp;&nbsp;&nbsp;&nbsp;&nbsp;&nbsp;&nbsp;&nbsp;&nbsp;</p>\\n\",\"image\":\"\",\"audio\":\"\",\"audioName\":\"\",\"hint\":\"\"},\"options\":[{\"text\":\"<p>கனி &ndash; மலர்தல் &ndash; இளந்தளிர் &ndash; முளைத்தல்</p>\\n\",\"image\":\"\",\"audio\":\"\",\"audioName\":\"\",\"hint\":\"\",\"isCorrect\":false,\"$$hashKey\":\"object:1215\"},{\"text\":\"<p>முளைத்தல் &ndash; இளந்தளிர் &ndash; மலர்தல்&nbsp; - கனி உருவாதல்</p>\\n\",\"image\":\"\",\"audio\":\"\",\"audioName\":\"\",\"hint\":\"\",\"isCorrect\":true,\"$$hashKey\":\"object:1216\"},{\"text\":\"<p>மலர்தல் &ndash; கனி உருவாதல் &ndash; இளந்தளிர் &ndash; முளைத்தல்</p>\\n\",\"image\":\"\",\"audio\":\"\",\"audioName\":\"\",\"isCorrect\":false,\"$$hashKey\":\"object:1226\"},{\"text\":\"<p>இளந்தளிர் &ndash; மலர்தல் &ndash; கனிதல் &ndash; முளைத்தல்</p>\\n\",\"image\":\"\",\"audio\":\"\",\"audioName\":\"\",\"isCorrect\":false,\"$$hashKey\":\"object:1231\"}],\"questionCount\":0,\"media\":[]},\"config\":{\"metadata\":{\"max_score\":1,\"isShuffleOption\":true,\"isPartialScore\":true,\"templateType\":\"Horizontal\",\"name\":\"LCMMQK-Q28-படிம வளர்ச்சி (development) படிநிலையை சரியாக வரிசைப்படுத்து.\",\"title\":\"LCMMQK-Q28-படிம வளர்ச்சி (development) படிநிலையை சரியாக வரிசைப்படுத்து.\",\"board\":\"State (Tamil Nadu)\",\"medium\":\"Tamil\",\"gradeLevel\":[\"Class 11\"],\"subject\":\"Botany\",\"qlevel\":\"MEDIUM\",\"category\":\"MCQ\"},\"max_time\":0,\"max_score\":1,\"partial_scoring\":true,\"layout\":\"Horizontal\",\"isShuffleOption\":true,\"questionCount\":1},\"media\":[]}}","createdOn":"2018-10-22T13:11:40.547+0000","gradeLevel":["Class 11"],"isShuffleOption":true,"appId":"prod.diksha.portal","options":[{"answer":true,"value":{"type":"text","asset":"1","resvalue":0,"resindex":0}}],"lastUpdatedOn":"2018-10-22T13:11:40.547+0000","identifier":"do_31261743227328102421312","consumerId":"150610ca-4ffb-4e0a-b4ef-c1305e9100d5","version":2,"versionKey":"1540213900547","framework":"tn_k-12_1","createdBy":"96e0cff3-d124-42b0-a5e3-38d0576ee661","max_score":1,"name":"LCMMQK-Q28-படிம வளர்ச்சி (development) படிநிலையை சரியாக வரிசைப்படுத்து.","template_id":"NA","category":"MCQ","board":"State (Tamil Nadu)","status":"Live"}}}