{"id":"ekstep.learning.item.read","ver":"1.0","ts":"2018-10-26T07:59:13ZZ","params":{"resmsgid":"ca32c7a2-3084-479b-bb55-b9286b2c15bf","msgid":null,"err":null,"status":"successful","errmsg":null},"responseCode":"OK","result":{"assessment_item":{"template":"NA","templateType":"Vertical","isPartialScore":true,"itemType":"UNIT","code":"NA","data":"{\"plugin\":{\"id\":\"org.ekstep.questionunit.mcq\",\"version\":\"1.1\",\"templateId\":\"horizontalMCQ\"},\"data\":{\"question\":{\"text\":\"<p><span style=\\\"color:#c0392b;\\\"><span style=\\\"font-size:1.714285714em;\\\"><strong>&nbsp;جنت بے نظیر کس جگہ کو کہتے ہیں؟</strong></span></span></p>\\n\",\"image\":\"\",\"audio\":\"\",\"audioName\":\"\",\"hint\":\"\"},\"options\":[{\"text\":\"<p><span style=\\\"font-size:2em;\\\"><strong>دہلی</strong></span></p>\\n\",\"image\":\"\",\"audio\":\"\",\"audioName\":\"\",\"hint\":\"\",\"isCorrect\":false,\"$$hashKey\":\"object:7404\"},{\"text\":\"<p><strong><span style=\\\"font-size:1.857142857em;\\\">کولکتہ</span></strong></p>\\n\",\"image\":\"\",\"audio\":\"\",\"audioName\":\"\",\"hint\":\"\",\"isCorrect\":false,\"$$hashKey\":\"object:7405\"},{\"text\":\"<p><span style=\\\"font-size:1.857142857em;\\\"><strong>کشمیر</strong></span></p>\\n\",\"image\":\"\",\"audio\":\"\",\"audioName\":\"\",\"isCorrect\":true,\"$$hashKey\":\"object:7415\"},{\"text\":\"<p><strong><span style=\\\"font-size:2em;\\\">حیدر آباد</span></strong></p>\\n\",\"image\":\"\",\"audio\":\"\",\"audioName\":\"\",\"isCorrect\":false,\"$$hashKey\":\"object:7420\"}],\"questionCount\":0,\"media\":[]},\"config\":{\"metadata\":{\"max_score\":1,\"isShuffleOption\":false,\"isPartialScore\":true,\"templateType\":\"Vertical\",\"name\":\"زمین کا جنت کس جگہ کو کہتے ہیں\\n\",\"title\":\"زمین کا جنت کس جگہ کو کہتے ہیں\\n\",\"description\":\"جنت\",\"board\":\"State(Jammu & Kashmir)\",\"medium\":\"Urdu\",\"gradeLevel\":[\"Class 5\"],\"subject\":\"Urdu\",\"qlevel\":\"EASY\",\"category\":\"MCQ\"},\"max_time\":0,\"max_score\":1,\"partial_scoring\":true,\"layout\":\"Vertical\",\"isShuffleOption\":false,\"questionCount\":1},\"media\":[]}","subject":"Urdu","qlevel":"EASY","channel":"01254592085869363222","description":"جنت","language":["English"],"medium":"Urdu","title":"زمین کا جنت کس جگہ کو کہتے ہیں\n","type":"mcq","body":"{\"data\":{\"plugin\":{\"id\":\"org.ekstep.questionunit.mcq\",\"version\":\"1.1\",\"templateId\":\"horizontalMCQ\"},\"data\":{\"question\":{\"text\":\"<p><span style=\\\"color:#c0392b;\\\"><span style=\\\"font-size:1.714285714em;\\\"><strong>&nbsp;جنت بے نظیر کس جگہ کو کہتے ہیں؟</strong></span></span></p>\\n\",\"image\":\"\",\"audio\":\"\",\"audioName\":\"\",\"hint\":\"\"},\"options\":[{\"text\":\"<p><span style=\\\"font-size:2em;\\\"><strong>دہلی</strong></span></p>\\n\",\"image\":\"\",\"audio\":\"\",\"audioName\":\"\",\"hint\":\"\",\"isCorrect\":false,\"$$hashKey\":\"object:7404\"},{\"text\":\"<p><strong><span style=\\\"font-size:1.857142857em;\\\">کولکتہ</span></strong></p>\\n\",\"image\":\"\",\"audio\":\"\",\"audioName\":\"\",\"hint\":\"\",\"isCorrect\":false,\"$$hashKey\":\"object:7405\"},{\"text\":\"<p><span style=\\\"font-size:1.857142857em;\\\"><strong>کشمیر</strong></span></p>\\n\",\"image\":\"\",\"audio\":\"\",\"audioName\":\"\",\"isCorrect\":true,\"$$hashKey\":\"object:7415\"},{\"text\":\"<p><strong><span style=\\\"font-size:2em;\\\">حیدر آباد</span></strong></p>\\n\",\"image\":\"\",\"audio\":\"\",\"audioName\":\"\",\"isCorrect\":false,\"$$hashKey\":\"object:7420\"}],\"questionCount\":0,\"media\":[]},\"config\":{\"metadata\":{\"data\":{\"plugin\":{\"id\":\"org.ekstep.questionunit.mcq\",\"version\":\"1.1\",\"templateId\":\"horizontalMCQ\"},\"data\":{\"question\":{\"text\":\"<p><span style=\\\"color:#c0392b;\\\"><span style=\\\"font-size:1.714285714em;\\\"><strong>&nbsp;جنت بے نظیر کس جگہ کو کہتے ہیں؟</strong></span></span></p>\\n\",\"image\":\"\",\"audio\":\"\",\"audioName\":\"\",\"hint\":\"\"},\"options\":[{\"text\":\"<p><span style=\\\"font-size:2em;\\\"><strong>دہلی</strong></span></p>\\n\",\"image\":\"\",\"audio\":\"\",\"audioName\":\"\",\"hint\":\"\",\"isCorrect\":false,\"$$hashKey\":\"object:7404\"},{\"text\":\"<p><strong><span style=\\\"font-size:1.857142857em;\\\">کولکتہ</span></strong></p>\\n\",\"image\":\"\",\"audio\":\"\",\"audioName\":\"\",\"hint\":\"\",\"isCorrect\":false,\"$$hashKey\":\"object:7405\"},{\"text\":\"<p><span style=\\\"font-size:1.857142857em;\\\"><strong>کشمیر</strong></span></p>\\n\",\"image\":\"\",\"audio\":\"\",\"audioName\":\"\",\"isCorrect\":true,\"$$hashKey\":\"object:7415\"},{\"text\":\"<p><strong><span style=\\\"font-size:2em;\\\">حیدر آباد</span></strong></p>\\n\",\"image\":\"\",\"audio\":\"\",\"audioName\":\"\",\"isCorrect\":false,\"$$hashKey\":\"object:7420\"}],\"questionCount\":0,\"media\":[]},\"config\":{\"metadata\":{\"max_score\":1,\"isShuffleOption\":false,\"isPartialScore\":true,\"templateType\":\"Vertical\",\"name\":\"زمین کا جنت کس جگہ کو کہتے ہیں\\n\",\"title\":\"زمین کا جنت کس جگہ کو کہتے ہیں\\n\",\"description\":\"جنت\",\"board\":\"State(Jammu & Kashmir)\",\"medium\":\"Urdu\",\"gradeLevel\":[\"Class 5\"],\"subject\":\"Urdu\",\"qlevel\":\"EASY\",\"category\":\"MCQ\"},\"max_time\":0,\"max_score\":1,\"partial_scoring\":true,\"layout\":\"Vertical\",\"isShuffleOption\":false,\"questionCount\":1},\"media\":[]},\"medium\":\"Urdu\",\"questionTitle\":\"زمین کا جنت کس جگہ کو کہتے ہیں\\n\",\"qlevel\":\"EASY\",\"subject\":\"Urdu\",\"board\":\"State(Jammu & Kashmir)\",\"templateType\":\"Vertical\",\"isPartialScore\":true,\"gradeLevel\":[\"Class 5\"],\"isShuffleOption\":false,\"questionDesc\":\"جنت\",\"max_score\":1,\"name\":\"زمین کا جنت کس جگہ کو کہتے ہیں\\n\",\"title\":\"زمین کا جنت کس جگہ کو کہتے ہیں\\n\",\"description\":\"جنت\",\"category\":\"MCQ\"},\"max_time\":0,\"max_score\":1,\"partial_scoring\":true,\"layout\":\"Vertical\",\"isShuffleOption\":false,\"questionCount\":1},\"media\":[]}}","createdOn":"2018-10-25T14:33:39.015+0000","gradeLevel":["Class 5"],"isShuffleOption":false,"appId":"prod.diksha.portal","options":[{"answer":true,"value":{"type":"text","asset":"1","resvalue":0,"resindex":0}}],"lastUpdatedOn":"2018-10-26T05:19:32.981+0000","questionDesc":"جنت","identifier":"do_31261959593177088022103","questionTitle":"زمین کا جنت کس جگہ کو کہتے ہیں\n","consumerId":"e85bcfb5-a8c2-4e65-87a2-0ebb43b45f01","version":2,"versionKey":"1540531172981","framework":"NCF","createdBy":"7072abef-63a2-40f5-b853-64ec522e466a","max_score":1,"name":"زمین کا جنت کس جگہ کو کہتے ہیں\n","template_id":"NA","category":"MCQ","board":"State(Jammu & Kashmir)","status":"Live"}}}