{"id":"ekstep.learning.item.read","ver":"1.0","ts":"2018-10-26T07:59:09ZZ","params":{"resmsgid":"56ece847-d320-4fe5-8789-f4b594544f2f","msgid":null,"err":null,"status":"successful","errmsg":null},"responseCode":"OK","result":{"assessment_item":{"template":"NA","templateType":"Horizontal","isPartialScore":true,"itemType":"UNIT","code":"NA","data":"{\"plugin\":{\"id\":\"org.ekstep.questionunit.mcq\",\"version\":\"1.1\",\"templateId\":\"horizontalMCQ\"},\"data\":{\"question\":{\"text\":\"<p>How manager&rsquo;s commission on net profit after charging such commission is computed?</p>\\n\",\"image\":\"\",\"audio\":\"\",\"audioName\":\"\",\"hint\":\"\"},\"options\":[{\"text\":\"<p>Net profit before charging such commission x Rate of commission / 100</p>\\n\",\"image\":\"\",\"audio\":\"\",\"audioName\":\"\",\"hint\":\"\",\"isCorrect\":false,\"$$hashKey\":\"object:1185\"},{\"text\":\"<p>Net profit before charging such commission x Rate of commission / (100 + rate of commission)</p>\\n\",\"image\":\"\",\"audio\":\"\",\"audioName\":\"\",\"hint\":\"\",\"isCorrect\":true,\"$$hashKey\":\"object:1186\"},{\"text\":\"<p>Net profit after charging such commission x Rate of commission / (100 &ndash; rate of&nbsp; commission)</p>\\n\",\"image\":\"\",\"audio\":\"\",\"audioName\":\"\",\"isCorrect\":false,\"$$hashKey\":\"object:1196\"},{\"text\":\"<p>Net profit after charging such commission x Rate of commission / (100 + rate of commission)</p>\\n\",\"image\":\"\",\"audio\":\"\",\"audioName\":\"\",\"isCorrect\":false,\"$$hashKey\":\"object:1201\"}],\"questionCount\":0,\"media\":[]},\"config\":{\"metadata\":{\"max_score\":1,\"isShuffleOption\":true,\"isPartialScore\":true,\"templateType\":\"Horizontal\",\"name\":\"How manager’s commission on net profit after charging such commission is computed?\\n\",\"title\":\"How manager’s commission on net profit after charging such commission is computed?\\n\",\"board\":\"State (Tamil Nadu)\",\"medium\":\"English\",\"gradeLevel\":[\"Class 11\"],\"subject\":\"Accountancy Volume 2\",\"qlevel\":\"EASY\",\"category\":\"MCQ\"},\"max_time\":0,\"max_score\":1,\"partial_scoring\":true,\"layout\":\"Horizontal\",\"isShuffleOption\":true,\"questionCount\":1},\"media\":[]}","subject":"Accountancy Volume 2","qlevel":"EASY","channel":"01235953109336064029450","language":["English"],"medium":"English","title":"AKSTL4 Q10.How manager’s commission on net profit after charging such commission is computed?","type":"mcq","body":"{\"data\":{\"plugin\":{\"id\":\"org.ekstep.questionunit.mcq\",\"version\":\"1.1\",\"templateId\":\"horizontalMCQ\"},\"data\":{\"question\":{\"text\":\"<p>How manager&rsquo;s commission on net profit after charging such commission is computed?</p>\\n\",\"image\":\"\",\"audio\":\"\",\"audioName\":\"\",\"hint\":\"\"},\"options\":[{\"text\":\"<p>Net profit before charging such commission x Rate of commission / 100</p>\\n\",\"image\":\"\",\"audio\":\"\",\"audioName\":\"\",\"hint\":\"\",\"isCorrect\":false,\"$$hashKey\":\"object:1185\"},{\"text\":\"<p>Net profit before charging such commission x Rate of commission / (100 + rate of commission)</p>\\n\",\"image\":\"\",\"audio\":\"\",\"audioName\":\"\",\"hint\":\"\",\"isCorrect\":true,\"$$hashKey\":\"object:1186\"},{\"text\":\"<p>Net profit after charging such commission x Rate of commission / (100 &ndash; rate of&nbsp; commission)</p>\\n\",\"image\":\"\",\"audio\":\"\",\"audioName\":\"\",\"isCorrect\":false,\"$$hashKey\":\"object:1196\"},{\"text\":\"<p>Net profit after charging such commission x Rate of commission / (100 + rate of commission)</p>\\n\",\"image\":\"\",\"audio\":\"\",\"audioName\":\"\",\"isCorrect\":false,\"$$hashKey\":\"object:1201\"}],\"questionCount\":0,\"media\":[]},\"config\":{\"metadata\":{\"data\":{\"plugin\":{\"id\":\"org.ekstep.questionunit.mcq\",\"version\":\"1.1\",\"templateId\":\"horizontalMCQ\"},\"data\":{\"question\":{\"text\":\"<p>How manager&rsquo;s commission on net profit after charging such commission is computed?</p>\\n\",\"image\":\"\",\"audio\":\"\",\"audioName\":\"\",\"hint\":\"\"},\"options\":[{\"text\":\"<p>Net profit before charging such commission x Rate of commission / 100</p>\\n\",\"image\":\"\",\"audio\":\"\",\"audioName\":\"\",\"hint\":\"\",\"isCorrect\":false,\"$$hashKey\":\"object:1185\"},{\"text\":\"<p>Net profit before charging such commission x Rate of commission / (100 + rate of commission)</p>\\n\",\"image\":\"\",\"audio\":\"\",\"audioName\":\"\",\"hint\":\"\",\"isCorrect\":true,\"$$hashKey\":\"object:1186\"},{\"text\":\"<p>Net profit after charging such commission x Rate of commission / (100 &ndash; rate of&nbsp; commission)</p>\\n\",\"image\":\"\",\"audio\":\"\",\"audioName\":\"\",\"isCorrect\":false,\"$$hashKey\":\"object:1196\"},{\"text\":\"<p>Net profit after charging such commission x Rate of commission / (100 + rate of commission)</p>\\n\",\"image\":\"\",\"audio\":\"\",\"audioName\":\"\",\"isCorrect\":false,\"$$hashKey\":\"object:1201\"}],\"questionCount\":0,\"media\":[]},\"config\":{\"metadata\":{\"max_score\":1,\"isShuffleOption\":true,\"isPartialScore\":true,\"templateType\":\"Horizontal\",\"name\":\"How manager’s commission on net profit after charging such commission is computed?\\n\",\"title\":\"How manager’s commission on net profit after charging such commission is computed?\\n\",\"board\":\"State (Tamil Nadu)\",\"medium\":\"English\",\"gradeLevel\":[\"Class 11\"],\"subject\":\"Accountancy Volume 2\",\"qlevel\":\"EASY\",\"category\":\"MCQ\"},\"max_time\":0,\"max_score\":1,\"partial_scoring\":true,\"layout\":\"Horizontal\",\"isShuffleOption\":true,\"questionCount\":1},\"media\":[]},\"medium\":\"English\",\"questionTitle\":\"How manager’s commission on net profit after charging such commission is computed?\\n\",\"qlevel\":\"EASY\",\"subject\":\"Accountancy Volume 2\",\"board\":\"State (Tamil Nadu)\",\"templateType\":\"Horizontal\",\"isPartialScore\":true,\"gradeLevel\":[\"Class 11\"],\"isShuffleOption\":true,\"max_score\":1,\"name\":\"AKSTL4 Q10.How manager’s commission on net profit after charging such commission is computed?\",\"title\":\"AKSTL4 Q10.How manager’s commission on net profit after charging such commission is computed?\",\"category\":\"MCQ\"},\"max_time\":0,\"max_score\":1,\"partial_scoring\":true,\"layout\":\"Horizontal\",\"isShuffleOption\":true,\"questionCount\":1},\"media\":[]}}","createdOn":"2018-10-17T07:33:21.092+0000","gradeLevel":["Class 11"],"isShuffleOption":true,"appId":"prod.diksha.portal","options":[{"answer":true,"value":{"type":"text","asset":"1","resvalue":0,"resindex":0}}],"lastUpdatedOn":"2018-10-17T07:33:57.140+0000","identifier":"do_3126137270361456641527","questionTitle":"How manager’s commission on net profit after charging such commission is computed?\n","consumerId":"0ee329c3-7614-431f-b884-b04ac5e19d21","version":2,"versionKey":"1539761637140","framework":"tn_k-12_1","createdBy":"9bae135b-a7ae-4bf4-9392-b8184dd2a671","max_score":1,"name":"AKSTL4 Q10.How manager’s commission on net profit after charging such commission is computed?","template_id":"NA","category":"MCQ","board":"State (Tamil Nadu)","status":"Live"}}}