{"id":"ekstep.learning.item.read","ver":"1.0","ts":"2018-10-26T07:23:53ZZ","params":{"resmsgid":"cf80f443-e624-44e8-b52e-6ecaf438055a","msgid":null,"err":null,"status":"successful","errmsg":null},"responseCode":"OK","result":{"assessment_item":{"templateType":"Horizontal","template":"NA","isPartialScore":true,"itemType":"UNIT","code":"NA","subject":"Microbiology","qlevel":"MEDIUM","channel":"01235953109336064029450","language":["English"],"mimeType":"application/vnd.ekstep.ecml-archive","medium":"Tamil","type":"mcq","title":"7Q5QQGQ25 _______ சாயத்துடன் இணைந்து கரையாத கூட்டுப்பொருளை உருவாக்குகிறது.","body":"{\"data\":{\"plugin\":{\"id\":\"org.ekstep.questionunit.mcq\",\"version\":\"1.1\",\"templateId\":\"horizontalMCQ\"},\"data\":{\"question\":{\"text\":\"<p>_______ சாயத்துடன் இணைந்து கரையாத கூட்டுப்பொருளை உருவாக்குகிறது.</p>\\n\",\"image\":\"\",\"audio\":\"\",\"audioName\":\"\",\"hint\":\"\"},\"options\":[{\"text\":\"<p>சாஃபரின்</p>\\n\",\"image\":\"\",\"audio\":\"\",\"audioName\":\"\",\"hint\":\"\",\"isCorrect\":false,\"$$hashKey\":\"object:1863\"},{\"text\":\"<p>மெத்திலீன் புளூ</p>\\n\",\"image\":\"\",\"audio\":\"\",\"audioName\":\"\",\"hint\":\"\",\"isCorrect\":false,\"$$hashKey\":\"object:1864\"},{\"text\":\"<p>நிறம் நிறுத்தி</p>\\n\",\"image\":\"\",\"audio\":\"\",\"audioName\":\"\",\"isCorrect\":true,\"$$hashKey\":\"object:1874\"},{\"text\":\"<p>முதன்மை சாயம்</p>\\n\",\"image\":\"\",\"audio\":\"\",\"audioName\":\"\",\"isCorrect\":false,\"$$hashKey\":\"object:1879\"}],\"questionCount\":0,\"media\":[]},\"config\":{\"metadata\":{\"max_score\":1,\"isShuffleOption\":true,\"isPartialScore\":true,\"templateType\":\"Horizontal\",\"name\":\"7Q5QQGQ25 _______ சாயத்துடன் இணைந்து கரையாத கூட்டுப்பொருளை உருவாக்குகிறது.\",\"title\":\"7Q5QQGQ25 _______ சாயத்துடன் இணைந்து கரையாத கூட்டுப்பொருளை உருவாக்குகிறது.\",\"board\":\"State (Tamil Nadu)\",\"medium\":\"Tamil\",\"gradeLevel\":[\"Class 11\"],\"subject\":\"Microbiology\",\"qlevel\":\"MEDIUM\",\"contentType\":\"Resource\",\"mimeType\":\"application/vnd.ekstep.ecml-archive\",\"category\":\"MCQ\"},\"max_time\":0,\"max_score\":1,\"partial_scoring\":true,\"layout\":\"Horizontal\",\"isShuffleOption\":true,\"questionCount\":1},\"media\":[]}}","createdOn":"2018-10-17T06:46:16.855+0000","gradeLevel":["Class 11"],"isShuffleOption":true,"appId":"prod.diksha.portal","options":[{"answer":true,"value":{"type":"text","asset":"1","resvalue":0,"resindex":0}}],"lastUpdatedOn":"2018-10-17T06:46:16.855+0000","contentType":"Resource","identifier":"do_3126137039000043521505","version":2,"versionKey":"1539758776855","framework":"tn_k-12_1","createdBy":"96e0cff3-d124-42b0-a5e3-38d0576ee661","max_score":1,"name":"7Q5QQGQ25 _______ சாயத்துடன் இணைந்து கரையாத கூட்டுப்பொருளை உருவாக்குகிறது.","template_id":"NA","category":"MCQ","board":"State (Tamil Nadu)","status":"Live"}}}