{"id":"ekstep.learning.item.read","ver":"1.0","ts":"2018-10-26T07:59:09ZZ","params":{"resmsgid":"cd584339-8962-4a73-827a-d5e1a7df4702","msgid":null,"err":null,"status":"successful","errmsg":null},"responseCode":"OK","result":{"assessment_item":{"templateType":"Horizontal","template":"NA","isPartialScore":true,"itemType":"UNIT","code":"NA","data":"{\"plugin\":{\"id\":\"org.ekstep.questionunit.mcq\",\"version\":\"1.1\",\"templateId\":\"horizontalMCQ\"},\"data\":{\"question\":{\"text\":\"<p>எலக்ட்ரான் கடத்து சங்கிலியில் ஆக்ஸிஜனேற்ற பாஸ்பரிகரணத்தில் கடைசி எலக்ட்ரான் ஏற்பி&nbsp;&nbsp;&nbsp;&nbsp;&nbsp;&nbsp;&nbsp;&nbsp;</p>\\n\",\"image\":\"\",\"audio\":\"\",\"audioName\":\"\",\"hint\":\"\"},\"options\":[{\"text\":\"<p>&nbsp;&nbsp;<span class=\\\"math-text\\\" data-math=\\\"H_2\\\" style=\\\"display: inline-block;\\\">H_2</span>&nbsp;&nbsp; &nbsp;&nbsp;&nbsp;&nbsp;&nbsp;&nbsp;&nbsp;&nbsp;&nbsp;&nbsp;&nbsp;&nbsp;&nbsp;&nbsp;&nbsp;&nbsp;&nbsp;&nbsp;&nbsp;&nbsp;&nbsp;&nbsp;&nbsp;&nbsp;&nbsp;&nbsp;&nbsp;&nbsp;</p>\\n\",\"image\":\"\",\"audio\":\"\",\"audioName\":\"\",\"hint\":\"\",\"isCorrect\":false,\"$$hashKey\":\"object:5448\"},{\"text\":\"<p>சைட்டோகுரோம்&nbsp;<span class=\\\"math-text\\\" data-math=\\\"a_3\\\" style=\\\"display: inline-block;\\\">a_3</span></p>\\n\",\"image\":\"\",\"audio\":\"\",\"audioName\":\"\",\"hint\":\"\",\"isCorrect\":true,\"$$hashKey\":\"object:5449\"},{\"text\":\"<p>சைட்டோகுரோம் b&nbsp;&nbsp;&nbsp;&nbsp;&nbsp;&nbsp;</p>\\n\",\"image\":\"\",\"audio\":\"\",\"audioName\":\"\",\"isCorrect\":false,\"$$hashKey\":\"object:5459\"},{\"text\":\"<p>&nbsp;&nbsp;<span class=\\\"math-text\\\" data-math=\\\"CO_2\\\" style=\\\"display: inline-block;\\\">CO_2</span></p>\\n\",\"image\":\"\",\"audio\":\"\",\"audioName\":\"\",\"isCorrect\":false,\"$$hashKey\":\"object:5464\"}],\"questionCount\":0,\"media\":[]},\"config\":{\"metadata\":{\"max_score\":1,\"isShuffleOption\":true,\"isPartialScore\":true,\"templateType\":\"Horizontal\",\"name\":\"LC4VMA-Q29-எலக்ட்ரான் கடத்து சங்கிலியில் ஆக்ஸிஜனேற்ற பாஸ்பரிகரணத்தில் கடைசி எலக்ட்ரான் ஏற்பி\",\"title\":\"LC4VMA-Q29-எலக்ட்ரான் கடத்து சங்கிலியில் ஆக்ஸிஜனேற்ற பாஸ்பரிகரணத்தில் கடைசி எலக்ட்ரான் ஏற்பி\",\"board\":\"State (Tamil Nadu)\",\"medium\":\"Tamil\",\"gradeLevel\":[\"Class 11\"],\"subject\":\"Botany\",\"qlevel\":\"MEDIUM\",\"contentType\":\"Resource\",\"mimeType\":\"application/vnd.ekstep.ecml-archive\",\"category\":\"MCQ\"},\"max_time\":0,\"max_score\":1,\"partial_scoring\":true,\"layout\":\"Horizontal\",\"isShuffleOption\":true,\"questionCount\":1},\"media\":[]}","subject":"Botany","qlevel":"MEDIUM","channel":"01235953109336064029450","language":["English"],"mimeType":"application/vnd.ekstep.ecml-archive","medium":"Tamil","type":"mcq","title":"LC4VMA-Q29-எலக்ட்ரான் கடத்து சங்கிலியில் ஆக்ஸிஜனேற்ற பாஸ்பரிகரணத்தில் கடைசி எலக்ட்ரான் ஏற்பி","body":"{\"data\":{\"plugin\":{\"id\":\"org.ekstep.questionunit.mcq\",\"version\":\"1.1\",\"templateId\":\"horizontalMCQ\"},\"data\":{\"question\":{\"text\":\"<p>எலக்ட்ரான் கடத்து சங்கிலியில் ஆக்ஸிஜனேற்ற பாஸ்பரிகரணத்தில் கடைசி எலக்ட்ரான் ஏற்பி&nbsp;&nbsp;&nbsp;&nbsp;&nbsp;&nbsp;&nbsp;&nbsp;</p>\\n\",\"image\":\"\",\"audio\":\"\",\"audioName\":\"\",\"hint\":\"\"},\"options\":[{\"text\":\"<p>&nbsp;&nbsp;<span class=\\\"math-text\\\" data-math=\\\"H_2\\\" style=\\\"display: inline-block;\\\">H_2</span>&nbsp;&nbsp; &nbsp;&nbsp;&nbsp;&nbsp;&nbsp;&nbsp;&nbsp;&nbsp;&nbsp;&nbsp;&nbsp;&nbsp;&nbsp;&nbsp;&nbsp;&nbsp;&nbsp;&nbsp;&nbsp;&nbsp;&nbsp;&nbsp;&nbsp;&nbsp;&nbsp;&nbsp;&nbsp;&nbsp;</p>\\n\",\"image\":\"\",\"audio\":\"\",\"audioName\":\"\",\"hint\":\"\",\"isCorrect\":false,\"$$hashKey\":\"object:5448\"},{\"text\":\"<p>சைட்டோகுரோம்&nbsp;<span class=\\\"math-text\\\" data-math=\\\"a_3\\\" style=\\\"display: inline-block;\\\">a_3</span></p>\\n\",\"image\":\"\",\"audio\":\"\",\"audioName\":\"\",\"hint\":\"\",\"isCorrect\":true,\"$$hashKey\":\"object:5449\"},{\"text\":\"<p>சைட்டோகுரோம் b&nbsp;&nbsp;&nbsp;&nbsp;&nbsp;&nbsp;</p>\\n\",\"image\":\"\",\"audio\":\"\",\"audioName\":\"\",\"isCorrect\":false,\"$$hashKey\":\"object:5459\"},{\"text\":\"<p>&nbsp;&nbsp;<span class=\\\"math-text\\\" data-math=\\\"CO_2\\\" style=\\\"display: inline-block;\\\">CO_2</span></p>\\n\",\"image\":\"\",\"audio\":\"\",\"audioName\":\"\",\"isCorrect\":false,\"$$hashKey\":\"object:5464\"}],\"questionCount\":0,\"media\":[]},\"config\":{\"metadata\":{\"data\":{\"plugin\":{\"id\":\"org.ekstep.questionunit.mcq\",\"version\":\"1.1\",\"templateId\":\"horizontalMCQ\"},\"data\":{\"question\":{\"text\":\"<p>எலக்ட்ரான் கடத்து சங்கிலியில் ஆக்ஸிஜனேற்ற பாஸ்பரிகரணத்தில் கடைசி எலக்ட்ரான் ஏற்பி&nbsp;&nbsp;&nbsp;&nbsp;&nbsp;&nbsp;&nbsp;&nbsp;</p>\\n\",\"image\":\"\",\"audio\":\"\",\"audioName\":\"\",\"hint\":\"\"},\"options\":[{\"text\":\"<p>&nbsp;&nbsp;<span class=\\\"math-text\\\" data-math=\\\"H_2\\\" style=\\\"display: inline-block;\\\">H_2</span>&nbsp;&nbsp; &nbsp;&nbsp;&nbsp;&nbsp;&nbsp;&nbsp;&nbsp;&nbsp;&nbsp;&nbsp;&nbsp;&nbsp;&nbsp;&nbsp;&nbsp;&nbsp;&nbsp;&nbsp;&nbsp;&nbsp;&nbsp;&nbsp;&nbsp;&nbsp;&nbsp;&nbsp;&nbsp;&nbsp;</p>\\n\",\"image\":\"\",\"audio\":\"\",\"audioName\":\"\",\"hint\":\"\",\"isCorrect\":false,\"$$hashKey\":\"object:5448\"},{\"text\":\"<p>சைட்டோகுரோம்&nbsp;<span class=\\\"math-text\\\" data-math=\\\"a_3\\\" style=\\\"display: inline-block;\\\">a_3</span></p>\\n\",\"image\":\"\",\"audio\":\"\",\"audioName\":\"\",\"hint\":\"\",\"isCorrect\":true,\"$$hashKey\":\"object:5449\"},{\"text\":\"<p>சைட்டோகுரோம் b&nbsp;&nbsp;&nbsp;&nbsp;&nbsp;&nbsp;</p>\\n\",\"image\":\"\",\"audio\":\"\",\"audioName\":\"\",\"isCorrect\":false,\"$$hashKey\":\"object:5459\"},{\"text\":\"<p>&nbsp;&nbsp;<span class=\\\"math-text\\\" data-math=\\\"CO_2\\\" style=\\\"display: inline-block;\\\">CO_2</span></p>\\n\",\"image\":\"\",\"audio\":\"\",\"audioName\":\"\",\"isCorrect\":false,\"$$hashKey\":\"object:5464\"}],\"questionCount\":0,\"media\":[]},\"config\":{\"metadata\":{\"max_score\":1,\"isShuffleOption\":true,\"isPartialScore\":true,\"templateType\":\"Horizontal\",\"name\":\"LC4VMA-Q29-எலக்ட்ரான் கடத்து சங்கிலியில் ஆக்ஸிஜனேற்ற பாஸ்பரிகரணத்தில் கடைசி எலக்ட்ரான் ஏற்பி\",\"title\":\"LC4VMA-Q29-எலக்ட்ரான் கடத்து சங்கிலியில் ஆக்ஸிஜனேற்ற பாஸ்பரிகரணத்தில் கடைசி எலக்ட்ரான் ஏற்பி\",\"board\":\"State (Tamil Nadu)\",\"medium\":\"Tamil\",\"gradeLevel\":[\"Class 11\"],\"subject\":\"Botany\",\"qlevel\":\"MEDIUM\",\"contentType\":\"Resource\",\"mimeType\":\"application/vnd.ekstep.ecml-archive\",\"category\":\"MCQ\"},\"max_time\":0,\"max_score\":1,\"partial_scoring\":true,\"layout\":\"Horizontal\",\"isShuffleOption\":true,\"questionCount\":1},\"media\":[]},\"medium\":\"Tamil\",\"questionTitle\":\"LC4VMA-Q29-எலக்ட்ரான் கடத்து சங்கிலியில் ஆக்ஸிஜனேற்ற பாஸ்பரிகரணத்தில் கடைசி எலக்ட்ரான் ஏற்பி\",\"qlevel\":\"MEDIUM\",\"subject\":\"Botany\",\"board\":\"State (Tamil Nadu)\",\"templateType\":\"Horizontal\",\"isPartialScore\":true,\"gradeLevel\":[\"Class 11\"],\"isShuffleOption\":true,\"max_score\":1,\"name\":\"LC4VMA-Q29-எலக்ட்ரான் கடத்து சங்கிலியில் ஆக்ஸிஜனேற்ற பாஸ்பரிகரணத்தில் கடைசி எலக்ட்ரான் ஏற்பி\",\"title\":\"LC4VMA-Q29-எலக்ட்ரான் கடத்து சங்கிலியில் ஆக்ஸிஜனேற்ற பாஸ்பரிகரணத்தில் கடைசி எலக்ட்ரான் ஏற்பி\",\"category\":\"MCQ\"},\"max_time\":0,\"max_score\":1,\"partial_scoring\":true,\"layout\":\"Horizontal\",\"isShuffleOption\":true,\"questionCount\":1},\"media\":[]}}","createdOn":"2018-10-23T08:07:35.821+0000","gradeLevel":["Class 11"],"isShuffleOption":true,"appId":"prod.diksha.portal","options":[{"answer":true,"value":{"type":"text","asset":"1","resvalue":0,"resindex":0}}],"lastUpdatedOn":"2018-10-25T07:24:00.592+0000","contentType":"Resource","identifier":"do_31261799060129382411199","questionTitle":"LC4VMA-Q29-எலக்ட்ரான் கடத்து சங்கிலியில் ஆக்ஸிஜனேற்ற பாஸ்பரிகரணத்தில் கடைசி எலக்ட்ரான் ஏற்பி","consumerId":"150610ca-4ffb-4e0a-b4ef-c1305e9100d5","version":2,"versionKey":"1540452240592","framework":"tn_k-12_1","createdBy":"96e0cff3-d124-42b0-a5e3-38d0576ee661","max_score":1,"name":"LC4VMA-Q29-எலக்ட்ரான் கடத்து சங்கிலியில் ஆக்ஸிஜனேற்ற பாஸ்பரிகரணத்தில் கடைசி எலக்ட்ரான் ஏற்பி","template_id":"NA","category":"MCQ","board":"State (Tamil Nadu)","status":"Live"}}}