{"id":"ekstep.learning.item.read","ver":"1.0","ts":"2018-10-26T07:59:11ZZ","params":{"resmsgid":"34cd9bd7-77b0-46fe-ace2-69e9eaa9a2b9","msgid":null,"err":null,"status":"successful","errmsg":null},"responseCode":"OK","result":{"assessment_item":{"templateType":"Horizontal","template":"NA","isPartialScore":true,"itemType":"UNIT","code":"NA","subject":"Social Studies","qlevel":"EASY","channel":"01248978648941363234","language":["English"],"medium":"Kannada","title":"ಭೂರತದಲ್ಲಿ ಅತೀ ಹೆಚ್ಚು ಅರಣ್ಯ ಪ್ರದೇಶ ಹೊಂದಿರುವ ರಾಜ್ಯ\n","type":"mcq","body":"{\"data\":{\"plugin\":{\"id\":\"org.ekstep.questionunit.mcq\",\"version\":\"1.1\",\"templateId\":\"horizontalMCQ\"},\"data\":{\"question\":{\"text\":\"<p>ಭೂರತದಲ್ಲಿ ಅತೀ ಹೆಚ್ಚು ಅರಣ್ಯ ಪ್ರದೇಶ ಹೊಂದಿರುವ ರಾಜ್ಯ</p>\\n\",\"image\":\"\",\"audio\":\"\",\"audioName\":\"\",\"hint\":\"\"},\"options\":[{\"text\":\"<p>ಕರ್ನಾಟದ&nbsp;</p>\\n\",\"image\":\"\",\"audio\":\"\",\"audioName\":\"\",\"hint\":\"\",\"isCorrect\":false,\"$$hashKey\":\"object:2992\"},{\"text\":\"<p>ಮಧ್ಯಪ್ರದೇಶ</p>\\n\",\"image\":\"\",\"audio\":\"\",\"audioName\":\"\",\"hint\":\"\",\"isCorrect\":true,\"$$hashKey\":\"object:2993\"},{\"text\":\"<p>ಅಸ್ಸಾಂ&nbsp;</p>\\n\",\"image\":\"\",\"audio\":\"\",\"audioName\":\"\",\"isCorrect\":false,\"$$hashKey\":\"object:3003\"},{\"text\":\"<p>ಕೇರಳ&nbsp;</p>\\n\",\"image\":\"\",\"audio\":\"\",\"audioName\":\"\",\"isCorrect\":false,\"$$hashKey\":\"object:3008\"}],\"questionCount\":0,\"media\":[]},\"config\":{\"metadata\":{\"max_score\":1,\"isShuffleOption\":false,\"isPartialScore\":true,\"templateType\":\"Horizontal\",\"name\":\"ಭೂರತದಲ್ಲಿ ಅತೀ ಹೆಚ್ಚು ಅರಣ್ಯ ಪ್ರದೇಶ ಹೊಂದಿರುವ ರಾಜ್ಯ\\n\",\"title\":\"ಭೂರತದಲ್ಲಿ ಅತೀ ಹೆಚ್ಚು ಅರಣ್ಯ ಪ್ರದೇಶ ಹೊಂದಿರುವ ರಾಜ್ಯ\\n\",\"board\":\"State (Karnataka)\",\"medium\":\"Kannada\",\"gradeLevel\":[\"Class 10\"],\"subject\":\"Social Studies\",\"qlevel\":\"EASY\",\"category\":\"MCQ\"},\"max_time\":0,\"max_score\":1,\"partial_scoring\":true,\"layout\":\"Horizontal\",\"isShuffleOption\":false,\"questionCount\":1},\"media\":[]}}","createdOn":"2018-10-23T06:34:52.141+0000","gradeLevel":["Class 10"],"isShuffleOption":false,"appId":"prod.diksha.portal","options":[{"answer":true,"value":{"type":"text","asset":"1","resvalue":0,"resindex":0}}],"lastUpdatedOn":"2018-10-23T06:34:52.141+0000","identifier":"do_31261794502361907211164","consumerId":"150610ca-4ffb-4e0a-b4ef-c1305e9100d5","version":2,"versionKey":"1540276492141","framework":"NCF","createdBy":"70b26dea-c518-450e-8ddd-31b52bc0da4b","max_score":1,"name":"ಭೂರತದಲ್ಲಿ ಅತೀ ಹೆಚ್ಚು ಅರಣ್ಯ ಪ್ರದೇಶ ಹೊಂದಿರುವ ರಾಜ್ಯ\n","template_id":"NA","category":"MCQ","board":"State (Karnataka)","status":"Live"}}}