{"id":"ekstep.learning.item.read","ver":"1.0","ts":"2018-10-26T07:29:46ZZ","params":{"resmsgid":"31e4766f-232f-4ac8-9c0c-adbac6f75421","msgid":null,"err":null,"status":"successful","errmsg":null},"responseCode":"OK","result":{"assessment_item":{"template":"NA","templateType":"Grid","isPartialScore":true,"itemType":"UNIT","code":"NA","subject":"Social Studies","qlevel":"MEDIUM","channel":"01254592085869363222","language":["English"],"medium":"English","title":"who is the President of Turkey?\n","type":"mcq","body":"{\"data\":{\"plugin\":{\"id\":\"org.ekstep.questionunit.mcq\",\"version\":\"1.1\",\"templateId\":\"horizontalMCQ\"},\"data\":{\"question\":{\"text\":\"<p>who is the President&nbsp;of Turkey?</p>\\n\",\"image\":\"\",\"audio\":\"\",\"audioName\":\"\",\"hint\":\"\"},\"options\":[{\"text\":\"<p>AK</p>\\n\",\"image\":\"\",\"audio\":\"\",\"audioName\":\"\",\"hint\":\"\",\"isCorrect\":false,\"$$hashKey\":\"object:12875\"},{\"text\":\"<p>Tuaib Ardogan&nbsp;</p>\\n\",\"image\":\"\",\"audio\":\"\",\"audioName\":\"\",\"hint\":\"\",\"isCorrect\":true,\"$$hashKey\":\"object:12876\"},{\"text\":\"<p>JK</p>\\n\",\"image\":\"\",\"audio\":\"\",\"audioName\":\"\",\"isCorrect\":false,\"$$hashKey\":\"object:12886\"},{\"text\":\"<p>Atta Turak&nbsp;</p>\\n\",\"image\":\"\",\"audio\":\"\",\"audioName\":\"\",\"isCorrect\":false,\"$$hashKey\":\"object:12891\"}],\"questionCount\":0,\"media\":[]},\"config\":{\"metadata\":{\"max_score\":1,\"isShuffleOption\":false,\"isPartialScore\":true,\"templateType\":\"Grid\",\"name\":\"who is the President of Turkey?\\n\",\"title\":\"who is the President of Turkey?\\n\",\"board\":\"State(Jammu & Kashmir)\",\"medium\":\"English\",\"gradeLevel\":[\"Class 5\"],\"subject\":\"Social Studies\",\"qlevel\":\"MEDIUM\",\"category\":\"MCQ\"},\"max_time\":0,\"max_score\":1,\"partial_scoring\":true,\"layout\":\"Vertical2\",\"isShuffleOption\":false,\"questionCount\":1},\"media\":[]}}","createdOn":"2018-10-25T06:46:29.874+0000","gradeLevel":["Class 5"],"isShuffleOption":false,"appId":"prod.diksha.portal","options":[{"answer":true,"value":{"type":"text","asset":"1","resvalue":0,"resindex":0}}],"lastUpdatedOn":"2018-10-25T06:46:29.874+0000","identifier":"do_31261936631705600011799","consumerId":"150610ca-4ffb-4e0a-b4ef-c1305e9100d5","version":2,"versionKey":"1540449989874","framework":"NCF","createdBy":"0f66015a-72ac-43fc-a0ac-afcf287219f5","max_score":1,"name":"who is the President of Turkey?\n","template_id":"NA","category":"MCQ","board":"State(Jammu & Kashmir)","status":"Live"}}}