{"id":"ekstep.learning.item.read","ver":"1.0","ts":"2018-10-26T07:45:37ZZ","params":{"resmsgid":"e30cb41d-5440-4f28-8611-fcc03a697755","msgid":null,"err":null,"status":"successful","errmsg":null},"responseCode":"OK","result":{"assessment_item":{"template":"NA","templateType":"Horizontal","isPartialScore":true,"itemType":"UNIT","code":"NA","subject":"Physics","qlevel":"MEDIUM","channel":"01235953109336064029450","language":["English"],"medium":"English","title":"BQ9CF2Q4 If m1 amount of water at temperature T1 is mixed with m2 amount of water at temperature T2, where m1> m2, then the temperature of mixed water is","type":"mcq","body":"{\"data\":{\"plugin\":{\"id\":\"org.ekstep.questionunit.mcq\",\"version\":\"1.1\",\"templateId\":\"horizontalMCQ\"},\"data\":{\"question\":{\"text\":\"<p style=\\\"margin-top:0in; margin-right:0in; margin-bottom:.0001pt\\\"><span style=\\\"font-size:12.0pt\\\"><span style=\\\"line-height:115%\\\"><span style=\\\"font-family:&quot;Arial Unicode MS&quot;,&quot;sans-serif&quot;\\\">If m<sub>1</sub> amount of water at temperature T<sub>1 </sub>is mixed with m<sub>2</sub> amount of water at temperature T<sub>2</sub>, where m<sub>1</sub>&gt; m<sub>2</sub>, then the temperature of mixed water is</span></span></span></p>\\n\",\"image\":\"\",\"audio\":\"\",\"audioName\":\"\",\"hint\":\"\"},\"options\":[{\"text\":\"<p>close to&nbsp;<span class=\\\"math-text\\\" data-math=\\\"T_1\\\" style=\\\"display: inline-block;\\\">T_1</span></p>\\n\",\"image\":\"\",\"audio\":\"\",\"audioName\":\"\",\"hint\":\"\",\"isCorrect\":true,\"$$hashKey\":\"object:923\"},{\"text\":\"<p>close to&nbsp;<span class=\\\"math-text\\\" data-math=\\\"T_2\\\" style=\\\"display: inline-block;\\\">T_2</span></p>\\n\",\"image\":\"\",\"audio\":\"\",\"audioName\":\"\",\"hint\":\"\",\"isCorrect\":false,\"$$hashKey\":\"object:924\"},{\"text\":\"<p>average of&nbsp;<span class=\\\"math-text\\\" data-math=\\\"T_1\\\" style=\\\"display: inline-block;\\\">T_1</span>&nbsp;and&nbsp;<span class=\\\"math-text\\\" data-math=\\\"T_2\\\" style=\\\"display: inline-block;\\\">T_2</span></p>\\n\",\"image\":\"\",\"audio\":\"\",\"audioName\":\"\",\"isCorrect\":false,\"$$hashKey\":\"object:934\"},{\"text\":\"<p>cannot be determined</p>\\n\",\"image\":\"\",\"audio\":\"\",\"audioName\":\"\",\"isCorrect\":false,\"$$hashKey\":\"object:939\"}],\"questionCount\":0,\"media\":[]},\"config\":{\"metadata\":{\"max_score\":1,\"isShuffleOption\":true,\"isPartialScore\":true,\"templateType\":\"Horizontal\",\"name\":\"BQ9CF2Q4 If m1 amount of water at temperature T1 is mixed with m2 amount of water at temperature T2, where m1> m2, then the temperature of mixed water is\",\"title\":\"BQ9CF2Q4 If m1 amount of water at temperature T1 is mixed with m2 amount of water at temperature T2, where m1> m2, then the temperature of mixed water is\",\"board\":\"State (Tamil Nadu)\",\"medium\":\"English\",\"gradeLevel\":[\"Class 11\"],\"subject\":\"Physics\",\"qlevel\":\"MEDIUM\",\"category\":\"MCQ\"},\"max_time\":0,\"max_score\":1,\"partial_scoring\":true,\"layout\":\"Horizontal\",\"isShuffleOption\":true,\"questionCount\":1},\"media\":[]}}","createdOn":"2018-10-15T09:07:23.169+0000","gradeLevel":["Class 11"],"isShuffleOption":true,"appId":"prod.diksha.portal","options":[{"answer":true,"value":{"type":"text","asset":"1","resvalue":0,"resindex":0}}],"lastUpdatedOn":"2018-10-15T09:07:23.169+0000","identifier":"do_3126123576784486401120","consumerId":"0ee329c3-7614-431f-b884-b04ac5e19d21","version":2,"versionKey":"1539594443169","framework":"tn_k-12_1","createdBy":"96e0cff3-d124-42b0-a5e3-38d0576ee661","max_score":1,"name":"BQ9CF2Q4 If m1 amount of water at temperature T1 is mixed with m2 amount of water at temperature T2, where m1> m2, then the temperature of mixed water is","template_id":"NA","category":"MCQ","board":"State (Tamil Nadu)","status":"Live"}}}