{"id":"ekstep.learning.item.read","ver":"1.0","ts":"2018-10-26T07:49:15ZZ","params":{"resmsgid":"48317e13-60f9-4043-9911-64d0fca394a0","msgid":null,"err":null,"status":"successful","errmsg":null},"responseCode":"OK","result":{"assessment_item":{"template":"NA","templateType":"Horizontal","isPartialScore":true,"itemType":"UNIT","code":"NA","subject":"Botany","qlevel":"EASY","channel":"01235953109336064029450","language":["English"],"medium":"Tamil","title":"LAAPAR-Q16-NPK என்பது எதைக் குறிக்கும்?","type":"mcq","body":"{\"data\":{\"plugin\":{\"id\":\"org.ekstep.questionunit.mcq\",\"version\":\"1.1\",\"templateId\":\"horizontalMCQ\"},\"data\":{\"question\":{\"text\":\"<p>NPK என்பது எதைக் குறிக்கும்?</p>\\n\",\"image\":\"\",\"audio\":\"\",\"audioName\":\"\",\"hint\":\"\"},\"options\":[{\"text\":\"<p>நைட்ரஜன், புரதம், கைனெட்டின்&nbsp;&nbsp;&nbsp;&nbsp;&nbsp;&nbsp;&nbsp;&nbsp;&nbsp;&nbsp;&nbsp;&nbsp;</p>\\n\",\"image\":\"\",\"audio\":\"\",\"audioName\":\"\",\"hint\":\"\",\"isCorrect\":false,\"$$hashKey\":\"object:1675\"},{\"text\":\"<p>நைட்ரஜன், புரதம், பொட்டாசியம்</p>\\n\",\"image\":\"\",\"audio\":\"\",\"audioName\":\"\",\"hint\":\"\",\"isCorrect\":false,\"$$hashKey\":\"object:1676\"},{\"text\":\"<p>&nbsp;நைட்ரஜன், பொட்டாசியம், கைனெட்டின்</p>\\n\",\"image\":\"\",\"audio\":\"\",\"audioName\":\"\",\"isCorrect\":false,\"$$hashKey\":\"object:1686\"},{\"text\":\"<p>நைட்ரஜன், பாஸ்பரஸ், பொட்டாசியம்</p>\\n\",\"image\":\"\",\"audio\":\"\",\"audioName\":\"\",\"isCorrect\":true,\"$$hashKey\":\"object:1691\"}],\"questionCount\":0,\"media\":[]},\"config\":{\"metadata\":{\"max_score\":1,\"isShuffleOption\":true,\"isPartialScore\":true,\"templateType\":\"Horizontal\",\"name\":\"LAAPAR-Q16-NPK என்பது எதைக் குறிக்கும்?\",\"title\":\"LAAPAR-Q16-NPK என்பது எதைக் குறிக்கும்?\",\"board\":\"State (Tamil Nadu)\",\"medium\":\"Tamil\",\"gradeLevel\":[\"Class 11\"],\"subject\":\"Botany\",\"qlevel\":\"EASY\",\"category\":\"MCQ\"},\"max_time\":0,\"max_score\":1,\"partial_scoring\":true,\"layout\":\"Horizontal\",\"isShuffleOption\":true,\"questionCount\":1},\"media\":[]}}","createdOn":"2018-10-23T11:29:33.279+0000","gradeLevel":["Class 11"],"isShuffleOption":true,"appId":"prod.diksha.portal","options":[{"answer":true,"value":{"type":"text","asset":"1","resvalue":0,"resindex":0}}],"lastUpdatedOn":"2018-10-23T11:29:33.279+0000","identifier":"do_31261808986750156821554","consumerId":"150610ca-4ffb-4e0a-b4ef-c1305e9100d5","version":2,"versionKey":"1540294173279","framework":"tn_k-12_1","createdBy":"96e0cff3-d124-42b0-a5e3-38d0576ee661","max_score":1,"name":"LAAPAR-Q16-NPK என்பது எதைக் குறிக்கும்?","template_id":"NA","category":"MCQ","board":"State (Tamil Nadu)","status":"Live"}}}