{"id":"ekstep.learning.item.read","ver":"1.0","ts":"2018-10-29T11:18:43ZZ","params":{"resmsgid":"42d99ec2-1951-4630-b1cc-2dfabe72d3a9","msgid":null,"err":null,"status":"successful","errmsg":null},"responseCode":"OK","result":{"assessment_item":{"template":"NA","itemType":"UNIT","code":"NA","subject":"Biology","qlevel":"MEDIUM","channel":"in.ekstep","language":["English"],"medium":"Telugu","type":"ftb","title":"Copy of - Check 2 +  2 = ____3 + 3 = ____","body":"{\"data\":{\"plugin\":{\"id\":\"org.ekstep.questionunit.ftb\",\"version\":\"1.0\",\"templateId\":\"ftbtemplate\"},\"data\":{\"question\":{\"text\":\"<p><span style=\\\"font-size: 18.5714px;\\\">2 +&nbsp; 2 = [[four]]</span></p>\\n\\n<p><span style=\\\"font-size: 18.5714px;\\\">3 + 3 = [[three]]</span></p>\\n\\n<p><span style=\\\"font-size: 18.5714px;\\\">4 + 4 = [[four]]</span></p>\\n\",\"image\":\"\",\"audio\":\"\",\"audioName\":\"\",\"keyboardConfig\":{\"keyboardType\":\"Device\",\"customKeys\":\"हो,गा,वि,रा,ट,क,र,ने,वि,शा,खा,प,त्त,न,म,ती,न\"}},\"answer\":[\"four\",\"three\",\"four\"],\"media\":[{\"id\":\"org.ekstep.keyboard.eras_icon\",\"src\":\"/content-plugins/org.ekstep.keyboard-1.0/renderer/assets/eras_icon.png\",\"assetId\":\"org.ekstep.keyboard.eras_icon\",\"type\":\"image\",\"preload\":true},{\"id\":\"org.ekstep.keyboard.language_icon\",\"src\":\"/content-plugins/org.ekstep.keyboard-1.0/renderer/assets/language_icon.png\",\"assetId\":\"org.ekstep.keyboard.language_icon\",\"type\":\"image\",\"preload\":true},{\"id\":\"org.ekstep.keyboard.hide_keyboard\",\"src\":\"/content-plugins/org.ekstep.keyboard-1.0/renderer/assets/keyboard.svg\",\"assetId\":\"org.ekstep.keyboard.hide_keyboard\",\"type\":\"image\",\"preload\":true}]},\"config\":{\"metadata\":{\"data\":{\"plugin\":{\"id\":\"org.ekstep.questionunit.ftb\",\"version\":\"1.0\",\"templateId\":\"ftbtemplate\"},\"data\":{\"question\":{\"text\":\"<p><span style=\\\"font-size: 18.5714px;\\\">2 +&nbsp; 2 = [[four]]</span></p>\\n\\n<p><span style=\\\"font-size: 18.5714px;\\\">3 + 3 = [[three]]</span></p>\\n\\n<p><span style=\\\"font-size: 18.5714px;\\\">4 + 4 = [[four]]</span></p>\\n\",\"image\":\"\",\"audio\":\"\",\"audioName\":\"\",\"keyboardConfig\":{\"keyboardType\":\"Device\",\"customKeys\":\"हो,गा,वि,रा,ट,क,र,ने,वि,शा,खा,प,त्त,न,म,ती,न\"}},\"answer\":[\"four\",\"three\"],\"media\":[{\"id\":\"org.ekstep.keyboard.eras_icon\",\"src\":\"/content-plugins/org.ekstep.keyboard-1.0/renderer/assets/eras_icon.png\",\"assetId\":\"org.ekstep.keyboard.eras_icon\",\"type\":\"image\",\"preload\":true},{\"id\":\"org.ekstep.keyboard.language_icon\",\"src\":\"/content-plugins/org.ekstep.keyboard-1.0/renderer/assets/language_icon.png\",\"assetId\":\"org.ekstep.keyboard.language_icon\",\"type\":\"image\",\"preload\":true},{\"id\":\"org.ekstep.keyboard.hide_keyboard\",\"src\":\"/content-plugins/org.ekstep.keyboard-1.0/renderer/assets/keyboard.svg\",\"assetId\":\"org.ekstep.keyboard.hide_keyboard\",\"type\":\"image\",\"preload\":true}]},\"config\":{\"metadata\":{\"max_score\":1,\"isShuffleOption\":false,\"isPartialScore\":true,\"templateType\":\"Horizontal\",\"name\":\"Check 2 +  2 = ____3 + 3 = ____\",\"title\":\"Check 2 +  2 = ____3 + 3 = ____\",\"board\":\"State (Andhra Pradesh)\",\"medium\":\"English\",\"gradeLevel\":[\"Class 8\"],\"subject\":\"Mathematics\",\"qlevel\":\"EASY\",\"category\":\"FTB\"},\"max_time\":0,\"max_score\":1,\"partial_scoring\":true,\"layout\":\"Horizontal\",\"isShuffleOption\":false,\"questionCount\":1},\"media\":[{\"id\":\"org.ekstep.keyboard.eras_icon\",\"src\":\"/content-plugins/org.ekstep.keyboard-1.0/renderer/assets/eras_icon.png\",\"assetId\":\"org.ekstep.keyboard.eras_icon\",\"type\":\"image\",\"preload\":true},{\"id\":\"org.ekstep.keyboard.language_icon\",\"src\":\"/content-plugins/org.ekstep.keyboard-1.0/renderer/assets/language_icon.png\",\"assetId\":\"org.ekstep.keyboard.language_icon\",\"type\":\"image\",\"preload\":true},{\"id\":\"org.ekstep.keyboard.hide_keyboard\",\"src\":\"/content-plugins/org.ekstep.keyboard-1.0/renderer/assets/keyboard.svg\",\"assetId\":\"org.ekstep.keyboard.hide_keyboard\",\"type\":\"image\",\"preload\":true}]},\"medium\":\"Telugu\",\"questionTitle\":\"Check 2 +  2 = ____3 + 3 = ____\",\"qlevel\":\"EASY\",\"subject\":\"Biology\",\"board\":\"State (Andhra Pradesh)\",\"templateType\":\"Horizontal\",\"isPartialScore\":true,\"gradeLevel\":[\"Class 9\",\"Class 8\"],\"isShuffleOption\":false,\"max_score\":1,\"name\":\"Check 2 +  2 = ____3 + 3 = ____\",\"title\":\"Copy of - Check 2 +  2 = ____3 + 3 = ____\",\"category\":\"FTB\"},\"max_time\":0,\"max_score\":1,\"partial_scoring\":true,\"layout\":\"Horizontal\",\"isShuffleOption\":false,\"questionCount\":1},\"media\":[{\"id\":\"org.ekstep.keyboard.eras_icon\",\"src\":\"/content-plugins/org.ekstep.keyboard-1.0/renderer/assets/eras_icon.png\",\"assetId\":\"org.ekstep.keyboard.eras_icon\",\"type\":\"image\",\"preload\":true},{\"id\":\"org.ekstep.keyboard.language_icon\",\"src\":\"/content-plugins/org.ekstep.keyboard-1.0/renderer/assets/language_icon.png\",\"assetId\":\"org.ekstep.keyboard.language_icon\",\"type\":\"image\",\"preload\":true},{\"id\":\"org.ekstep.keyboard.hide_keyboard\",\"src\":\"/content-plugins/org.ekstep.keyboard-1.0/renderer/assets/keyboard.svg\",\"assetId\":\"org.ekstep.keyboard.hide_keyboard\",\"type\":\"image\",\"preload\":true}]}}","createdOn":"2018-10-22T12:27:34.000+0000","gradeLevel":["Class 9","Class 8"],"isShuffleOption":false,"appId":"staging.diksha.portal","lastUpdatedOn":"2018-10-22T12:27:34.000+0000","identifier":"do_2126174105927761921163","question":"<p><span style=\"font-size: 18.5714px;\">2 +&nbsp; 2 = [[four]]</span></p>\n\n<p><span style=\"font-size: 18.5714px;\">3 + 3 = [[three]]</span></p>\n\n<p><span style=\"font-size: 18.5714px;\">4 + 4 = [[four]]</span></p>\n","consumerId":"a9cb3a83-a164-4bf0-aa49-b834cebf1c07","version":2,"versionKey":"1540211254000","framework":"NCF","answer":[{"answer":true,"value":{"type":"text","asset":"1"}}],"createdBy":"d32e170d-010b-4bc5-ae55-3ac5e547e35b","max_score":1,"name":"Copy of - Check 2 +  2 = ____3 + 3 = ____","template_id":"NA","category":"FTB","board":"State (Andhra Pradesh)","status":"Live"}}}