{"id":"ekstep.learning.item.read","ver":"1.0","ts":"2018-10-29T11:18:47ZZ","params":{"resmsgid":"e0dd9242-afb3-451c-82fa-c2c9429d163c","msgid":null,"err":null,"status":"successful","errmsg":null},"responseCode":"OK","result":{"assessment_item":{"template":"NA","templateType":"Horizontal","isPartialScore":true,"itemType":"UNIT","code":"NA","subject":"Science","qlevel":"EASY","channel":"0124758418460180480","description":"By umesh","language":["English"],"medium":"Hindi","type":"ftb","title":"umesh FTB check - what ____ my name\n","body":"{\"data\":{\"plugin\":{\"id\":\"org.ekstep.questionunit.ftb\",\"version\":\"1.0\",\"templateId\":\"ftbtemplate\"},\"data\":{\"question\":{\"text\":\"<p>umesh FTB check - what [[is]] my name</p>\\n\",\"image\":\"\",\"audio\":\"\",\"audioName\":\"\",\"keyboardConfig\":{\"keyboardType\":\"Custom\",\"customKeys\":\"a,i,f,s,d,g,b,w,g,x,t,w,j,k,z,s,g,w\"}},\"answer\":[\"is\"],\"media\":[{\"id\":\"org.ekstep.keyboard.eras_icon\",\"src\":\"/content-plugins/org.ekstep.keyboard-1.0/renderer/assets/eras_icon.png\",\"assetId\":\"org.ekstep.keyboard.eras_icon\",\"type\":\"image\",\"preload\":true},{\"id\":\"org.ekstep.keyboard.language_icon\",\"src\":\"/content-plugins/org.ekstep.keyboard-1.0/renderer/assets/language_icon.png\",\"assetId\":\"org.ekstep.keyboard.language_icon\",\"type\":\"image\",\"preload\":true},{\"id\":\"org.ekstep.keyboard.hide_keyboard\",\"src\":\"/content-plugins/org.ekstep.keyboard-1.0/renderer/assets/keyboard.svg\",\"assetId\":\"org.ekstep.keyboard.hide_keyboard\",\"type\":\"image\",\"preload\":true}]},\"config\":{\"metadata\":{\"max_score\":1,\"isShuffleOption\":false,\"isPartialScore\":true,\"templateType\":\"Horizontal\",\"name\":\"umesh FTB check - what ____ my name\\n\",\"title\":\"umesh FTB check - what ____ my name\\n\",\"description\":\"By umesh\",\"board\":\"State (Rajasthan)\",\"medium\":\"Hindi\",\"gradeLevel\":[\"Class 10\"],\"subject\":\"Science\",\"qlevel\":\"EASY\",\"category\":\"FTB\"},\"max_time\":0,\"max_score\":1,\"partial_scoring\":true,\"layout\":\"Horizontal\",\"isShuffleOption\":false,\"questionCount\":1},\"media\":[{\"id\":\"org.ekstep.keyboard.eras_icon\",\"src\":\"/content-plugins/org.ekstep.keyboard-1.0/renderer/assets/eras_icon.png\",\"assetId\":\"org.ekstep.keyboard.eras_icon\",\"type\":\"image\",\"preload\":true},{\"id\":\"org.ekstep.keyboard.language_icon\",\"src\":\"/content-plugins/org.ekstep.keyboard-1.0/renderer/assets/language_icon.png\",\"assetId\":\"org.ekstep.keyboard.language_icon\",\"type\":\"image\",\"preload\":true},{\"id\":\"org.ekstep.keyboard.hide_keyboard\",\"src\":\"/content-plugins/org.ekstep.keyboard-1.0/renderer/assets/keyboard.svg\",\"assetId\":\"org.ekstep.keyboard.hide_keyboard\",\"type\":\"image\",\"preload\":true}]}}","createdOn":"2018-10-16T08:52:22.054+0000","gradeLevel":["Class 10"],"isShuffleOption":false,"appId":"staging.diksha.portal","lastUpdatedOn":"2018-10-16T08:52:22.054+0000","identifier":"do_2126130580853063681266","consumerId":"a9cb3a83-a164-4bf0-aa49-b834cebf1c07","version":2,"versionKey":"1539679942054","framework":"rj_k-12_2","answer":[{"answer":true,"value":{"type":"text","asset":"1"}}],"createdBy":"9e607f86-21a8-445b-9854-42bbcf9f5a69","max_score":1,"name":"umesh FTB check - what ____ my name\n","template_id":"NA","category":"FTB","board":"State (Rajasthan)","status":"Live"}}}