{"id":"ekstep.learning.item.read","ver":"1.0","ts":"2018-10-29T11:18:44ZZ","params":{"resmsgid":"981c8c8a-d0cf-4428-accc-1363eeae385d","msgid":null,"err":null,"status":"successful","errmsg":null},"responseCode":"OK","result":{"assessment_item":{"templateType":"Horizontal","template":"NA","isPartialScore":true,"itemType":"UNIT","code":"NA","subject":"Urdu","qlevel":"DIFFICULT","channel":"0125683555607347207","language":["English"],"medium":"English","title":"Testing MTF\n","type":"mtf","body":"{\"data\":{\"plugin\":{\"id\":\"org.ekstep.questionunit.mtf\",\"version\":\"1.1\",\"templateId\":\"horizontalMTF\"},\"data\":{\"question\":{\"text\":\"<p>Testing MTF</p>\\n\",\"image\":\"\",\"audio\":\"\",\"audioName\":\"\",\"hint\":\"\"},\"option\":{\"optionsLHS\":[{\"text\":\"1\",\"image\":\"\",\"audio\":\"\",\"audioName\":\"\",\"hint\":\"\",\"index\":1,\"$$hashKey\":\"object:2170\"},{\"text\":\"2\",\"image\":\"\",\"audio\":\"\",\"audioName\":\"\",\"hint\":\"\",\"index\":2,\"$$hashKey\":\"object:2171\"},{\"text\":\"3\",\"image\":\"\",\"audio\":\"\",\"audioName\":\"\",\"hint\":\"\",\"index\":3,\"$$hashKey\":\"object:2172\"}],\"optionsRHS\":[{\"text\":\"1\",\"image\":\"\",\"audio\":\"\",\"audioName\":\"\",\"hint\":\"\",\"mapIndex\":1},{\"text\":\"2\",\"image\":\"\",\"audio\":\"\",\"audioName\":\"\",\"hint\":\"\",\"mapIndex\":2},{\"text\":\"3\",\"image\":\"\",\"audio\":\"\",\"audioName\":\"\",\"hint\":\"\",\"mapIndex\":3}],\"questionCount\":0},\"media\":[]},\"config\":{\"metadata\":{\"max_score\":2,\"isShuffleOption\":false,\"isPartialScore\":true,\"templateType\":\"Horizontal\",\"name\":\"Testing MTF\\n\",\"title\":\"Testing MTF\\n\",\"board\":\"NCERT\",\"gradeLevel\":[\"Class 3\",\"Class 3\"],\"subject\":\"Urdu\",\"qlevel\":\"DIFFICULT\",\"medium\":\"English\",\"category\":\"MTF\"},\"max_time\":0,\"max_score\":1,\"partial_scoring\":true,\"layout\":\"Horizontal\",\"isShuffleOption\":false,\"questionCount\":1},\"media\":[]}}","createdOn":"2018-10-23T10:00:06.073+0000","gradeLevel":["Class 3","Class 3"],"isShuffleOption":false,"appId":"staging.diksha.portal","lastUpdatedOn":"2018-10-23T10:00:06.073+0000","rhs_options":[{"value":{"type":"mixed","text":"इक","image":"","count":"","audio":"","resvalue":"इक","resindex":0},"index":0}],"identifier":"do_2126180458993500161252","consumerId":"a9cb3a83-a164-4bf0-aa49-b834cebf1c07","version":2,"versionKey":"1540288806073","lhs_options":[{"value":{"type":"mixed","text":"इक","image":"","count":"","audio":"","resvalue":"इक","resindex":0},"index":0}],"framework":"NCF","createdBy":"d32e170d-010b-4bc5-ae55-3ac5e547e35b","max_score":2,"name":"Testing MTF\n","template_id":"NA","category":"MTF","board":"NCERT","status":"Live"}}}